Workbook

Sheet SP List Extract
A1: ID | B1: Item Type | C1: Item Name | D1: PwC Owner | E1: Target Wave | F1: Actual Wave | G1: Design | H1: Build | I1: Test | J1: Sign-Off Requested | K1: Sign-Off Statu | L1: Nidhi Reviewed | M1: Nidhi's Feedback Incorporated | N1: Short Description | O1: Owner (NFP) | P1: Original Disposition (SOW) | Q1: Final Disposition Decision | R1: Status | S1: Target Build Date | T1: On Hold Reason | U1: Notes | V1: Story ID | W1: Target UAT Date | X1: Associated Aon Catalog Item (Adopt / Adapt) | Y1: Owner (Aon) | Z1: Design Session Date | AA1: Scope Changes | AB1: UAT Testers | AC1: Catalog Structure | AD1: Latest Update | AE1: Design Status | AF1: Design Planned Date | AG1: Design Forecasted Date | AH1: Design Actual Date | AI1: Build Status | AJ1: Build Planned Date | AK1: Build Forecasted Date | AL1: Build Actual Date | AM1: Test Status | AN1: Test Planned Date | AO1: Test Forecasted Date | AP1: Test Actual Date | AQ1: Deployed? | AR1: Deployed Planned Date | AS1: Deployed Forecasted Date | AT1: Deployed Actual Date | AU1: Order Guide Relation? | AV1: Onboarding Order Guide? | AW1: Missing / Placeholder Info | AX1: Currently Fulfilled by NFP SD? | AY1: Core Data Dependency | AZ1: RITM + Assignment Group | BA1: Item Type2 | BB1: Path
A2: CA001 | B2: Custom Application | C2: Primary Email Domain | D2: Javier | E2: 1.1 | F2: 1.1 | G2: Complete | H2: Complete | I2: Complete | J2: Done (08/31) | K2: Pending | N2: Custom application (with a custom table), nonscoped, that holds the primary email domain structure / format | O2: Antowan Jones | P2: Redesign | Q2: Redesign | R2: UAT In Progress | S2: 46227 | U2: User selects payroll company code during onboarding​. System presents available email domains​. Workflow determines email format and passes data to AD/Azure​. Managed via catalog item allowing add/update/deactivate actions | V2: STRY0146631 | W2: 46234 | AE2: Complete | AF2: 46234 | AG2: 46216 | AH2: 46216 | AI2: Complete | AJ2: 46241 | AK2: 46241 | AL2: 46220 | AM2: Not Started | AN2: 46247 | AO2: 46247 | AP2: 46227 | AQ2: Not Started | AR2: 46295 | AS2: 46295 | AU2: N/a | BA2: Item | BB2: sites/ext-AonNFPIntegration/Lists/ITSM Integration InScope Inventory
A3: INT001 | B3: Integration | C3: NFP Connect | D3: Javier | E3: 1.1 | F3: 1.1 | G3: Complete | H3: Complete | I3: In Progress | J3: Not Started | K3: Not Started | N3: Allows NFP Connect users (NFP Benefits Team – external users) to create incidents for NFP Connect issues they are facing. | O3: JP Subramaniam, Matt Fergo, Balajiprasad Ramesh | P3: Redesign | Q3: Redesign | R3: UAT In Progress | S3: 46232 | V3: STRY0146546 | W3: 46239 | AB3: • JP Subramaniam • Matt Fergo • Balajiprasad Ramesh • KamalNath Mudigati • Shashank Karanje | AE3: Complete | AF3: 46234 | AG3: 46227 | AH3: 46227 | AI3: Complete | AJ3: 46241 | AK3: 46241 | AL3: 46230 | AM3: Not Started | AN3: 46247 | AO3: 46247 | AP3: 46239 | AQ3: Not Started | AR3: 46295 | AS3: 46295 | AU3: N/a | BA3: Item | BB3: sites/ext-AonNFPIntegration/Lists/ITSM Integration InScope Inventory
A4: INT002 | B4: Integration | C4: BluePrint | D4: Javier | E4: 1.1 | F4: 1.1 | G4: Complete | H4: Complete | I4: In Progress | J4: Not Started | K4: Not Started | N4: Allows Blueprint users (NFP Member Firm users – external users) to create incidents for Blueprint issues they are facing. | O4: Bipin Sabhani, Shilpa Madduri (PM) | P4: Redesign | Q4: Redesign | R4: UAT In Progress | S4: 46232 | V4: STRY0146547 | W4: 46239 | AB4: • Bipin Sabhani • Shilpa Madduri | AE4: Complete | AF4: 46234 | AG4: 46227 | AH4: 46227 | AI4: Complete | AJ4: 46241 | AK4: 46241 | AL4: 46231 | AM4: Not Started | AN4: 46247 | AO4: 46247 | AP4: 46239 | AQ4: Not Started | AR4: 46295 | AS4: 46295 | AU4: N/a | BA4: Item | BB4: sites/ext-AonNFPIntegration/Lists/ITSM Integration InScope Inventory
A5: INT003 | B5: Integration | C5: NetOps Automation | D5: Javier | E5: 1.1 | F5: 1.1 | G5: Complete | H5: Complete | I5: Complete | J5: Done (08/31) | K5: Pending | L5: Pending Impln. | M5: Pending Impln. | N5: The NetBox application reads in records from the Site Code (u_site_code) table stored in ServiceNow | O5: Robert Spadaro, Ethan Katz | P5: Redesign | Q5: Redesign | R5: UAT In Progress | S5: 46220 | V5: STRY0146630 | W5: 46230 | AE5: Complete | AF5: 46234 | AG5: 46220 | AH5: 46220 | AI5: Complete | AJ5: 46241 | AK5: 46241 | AL5: 46227 | AM5: Not Started | AN5: 46247 | AO5: 46247 | AQ5: Not Started | AR5: 46295 | AS5: 46295 | AU5: N/a | BA5: Item | BB5: sites/ext-AonNFPIntegration/Lists/ITSM Integration InScope Inventory
A6: INT004 | B6: Integration | C6: NFP Cybersecurity | D6: N/a - Descoped | E6: N/a - Descoped | F6: N/a - Descoped | N6: Integrated with ServiceNow via a NFP Cybersecurity service account that creates incident records and manages them within ServiceNow via an automation, | O6: John Stratton | P6: Redesign | Q6: Retire / Descoped | R6: Descoped | Y6: Tim Lemm | AA6: Confirmed | AF6: 46234 | AM6: Not Started | AQ6: Not Started | AR6: 46295 | AS6: 46295 | AU6: N/a | BA6: Item | BB6: sites/ext-AonNFPIntegration/Lists/ITSM Integration InScope Inventory
A7: INT005 | B7: Integration | C7: Salesforce V2 Fingerprints | D7: Javier | E7: 1.1 | F7: 1.1 | G7: Complete | H7: Complete | I7: In Progress | J7: Not Started | K7: Not Started | L7: Not Received, Pending Implementation, Complete | M7: Not Received, Pending Implementation, Complete | N7: When an email is sent to the NFP ServiceNow instance with a certain ID in the subject line, an inbound email action (script within ServiceNow) creates a request using the Statement Mass Delete Catalog Item. | O7: Kris Lipetsky | P7: Redesign | Q7: Redesign | R7: UAT In Progress | S7: 46220 | U7: currently usingRMS RiskModeler | AR5858-QC001 as business_service later to be change to "Callidus ICM", Assignment Group is currently Global-Service Desk-Support, will later need to be changed to Benefits Commission Processing | V7: STRY0146532 | W7: 46230 | AB7: Rhoads McGuire - Kris Lipetzki | AE7: Complete | AF7: 46234 | AG7: 46216 | AH7: 46216 | AI7: Complete | AJ7: 46241 | AK7: 46241 | AL7: 46220 | AM7: Not Started | AN7: 46247 | AO7: 46247 | AP7: 46234 | AQ7: Not Started | AR7: 46295 | AS7: 46295 | AU7: N/a | BA7: Item | BB7: sites/ext-AonNFPIntegration/Lists/ITSM Integration InScope Inventory
A8: INT006 | B8: Integration | C8: PRTG | D8: N/a - Descoped | E8: N/a - Descoped | F8: N/a - Descoped | N8: Used for network monitoring, sending alerts / events to ServiceNow ITOM / EM | O8: Ethan Katz, Sagar Karur | P8: Redesign | Q8: Retire / Descoped | R8: Descoped | AA8: Confirmed | AF8: 46234 | AM8: Not Started | AQ8: Not Started | AR8: 46295 | AS8: 46295 | AU8: N/a | BA8: Item | BB8: sites/ext-AonNFPIntegration/Lists/ITSM Integration InScope Inventory
A9: INT007 | B9: Integration | C9: AD / Azure Data Factory | D9: Backlog | E9: 2.2 | F9: 2.2 | N9: *** Review Antowan's onboarding document for more details on this | O9: Antowan Jones | Q9: Redesign | R9: In Design | S9: 46262 | U9: As part of the onboarding/offboarding process, ServiceNow is integrated with AD. Technical POC: Khue Nguyen | W9: 46269 | AA9: Confirmed | AE9: In Progress | AF9: 46234 | AG9: 46241 | AI9: Not Started | AJ9: 46265 | AK9: 46265 | AM9: Not Started | AN9: 46268 | AO9: 46268 | AQ9: Not Started | AR9: 46295 | AS9: 46295 | AU9: Related to Onboarding & Transitions Order Guide | AV9: =TRUE() -> TRUE | BA9: Item | BB9: sites/ext-AonNFPIntegration/Lists/ITSM Integration InScope Inventory
A10: INT008 | B10: Integration | C10: Salesforce Back Office (SBO) | D10: Sowmya | E10: 1.1 | F10: 1.2 | G10: Complete | H10: Complete | I10: Not Started | J10: Not Started | K10: Not Started | L10: Not Started | M10: Not Started | N10: Related to Remote Work Request catalog item - integration needed as part of that workflow | O10: Jenna Davies | Q10: Redesign | R10: In Build Progress | S10: 46246 | W10: 46253 | AA10: N/A | AB10: Jenna Davies, Jerry Jenkins | AE10: Complete | AF10: 46234 | AG10: 46241 | AI10: In Progress | AJ10: 46241 | AK10: 46241 | AM10: In Progress | AN10: 46247 | AO10: 46247 | AQ10: Not Started | AR10: 46295 | AS10: 46295 | AU10: N/a | BA10: Item | BB10: sites/ext-AonNFPIntegration/Lists/ITSM Integration InScope Inventory
A11: INT009 | B11: Integration | C11: Azure (via Open Path flow) | D11: Sowmya | E11: 1.1 | F11: 1.2 | G11: Complete | H11: Complete | I11: In Progress | N11: API call to Azure / ADE once the Open Path catalog item is submitted (rather than a task generation) | O11: Anthony Papandrea | Q11: Redesign | R11: Ready for Testing | S11: 46246 | W11: 46253 | AA11: N/A | AB11: Chris Derico, Anthony Papandrea | AE11: In Progress | AF11: 46234 | AG11: 46241 | AI11: Complete | AJ11: 46241 | AK11: 46241 | AM11: Not Started | AN11: 46247 | AO11: 46247 | AQ11: Not Started | AR11: 46295 | AS11: 46295 | AU11: N/a | BA11: Item | BB11: sites/ext-AonNFPIntegration/Lists/ITSM Integration InScope Inventory
A12: PnC001 | B12: Catalog Item | C12: (P&C) Bank Account | D12: Somendra S.T. | E12: 3.1 | F12: 3.1 | O12: Teri C. | Q12: Redesign | R12: In Design | S12: 46288 | W12: 46295 | AA12: N/A | AU12: N/A | AV12: =FALSE() -> FALSE | BA12: Item | BB12: sites/ext-AonNFPIntegration/Lists/ITSM Integration InScope Inventory
A13: PnC002 | B13: Catalog Item | C13: (P&C) Broker and Carrier Billing Contact | D13: Somendra S.T. | E13: 3.1 | F13: 3.1 | O13: Teri C. | Q13: Redesign | R13: In Design | S13: 46288 | W13: 46295 | AA13: N/A | AU13: N/A | AV13: =FALSE() -> FALSE | BA13: Item | BB13: sites/ext-AonNFPIntegration/Lists/ITSM Integration InScope Inventory
A14: PnC003 | B14: Catalog Item | C14: (P&C) Document Design | D14: Somendra S.T. | E14: 3.1 | F14: 3.1 | O14: Teri C. | Q14: Redesign | R14: In Design | S14: 46288 | W14: 46295 | AA14: N/A | AU14: N/A | AV14: =FALSE() -> FALSE | BA14: Item | BB14: sites/ext-AonNFPIntegration/Lists/ITSM Integration InScope Inventory
A15: PnC004 | B15: Catalog Item | C15: (P&C) Download Resend/Discrepancy | D15: Somendra S.T. | E15: 3.1 | F15: 3.1 | O15: Teri C. | Q15: Redesign | R15: In Design | S15: 46288 | W15: 46295 | AA15: N/A | AU15: N/A | AV15: =FALSE() -> FALSE | BA15: Item | BB15: sites/ext-AonNFPIntegration/Lists/ITSM Integration InScope Inventory
A16: PnC005 | B16: Catalog Item | C16: (P&C) Employee Commission Agreement | D16: Somendra S.T. | E16: 3.1 | F16: 3.1 | O16: Teri C. | Q16: Redesign | R16: In Design | S16: 46288 | W16: 46295 | AA16: N/A | AU16: N/A | AV16: =FALSE() -> FALSE | BA16: Item | BB16: sites/ext-AonNFPIntegration/Lists/ITSM Integration InScope Inventory
A17: PnC006 | B17: Catalog Item | C17: (P&C) EMU Run Request | D17: Tarun | E17: 3.1 | F17: 3.1 | O17: Teri C. | Q17: Redesign | R17: In Design | S17: 46288 | W17: 46295 | AA17: N/A | AU17: N/A | AV17: =FALSE() -> FALSE | BA17: Item | BB17: sites/ext-AonNFPIntegration/Lists/ITSM Integration InScope Inventory
A18: PnC007 | B18: Catalog Item | C18: (P&C) Government Tax/Fee Request | D18: Somendra S.T. | E18: 3.1 | F18: 3.1 | O18: Teri C. | Q18: Redesign | R18: In Design | S18: 46288 | W18: 46295 | AA18: N/A | AU18: N/A | AV18: =FALSE() -> FALSE | BA18: Item | BB18: sites/ext-AonNFPIntegration/Lists/ITSM Integration InScope Inventory
A19: PnC008 | B19: Catalog Item | C19: (P&C) Issuing Company | D19: Somendra S.T. | E19: 3.1 | F19: 3.1 | O19: Teri C. | Q19: Redesign | R19: In Design | S19: 46288 | W19: 46295 | AA19: N/A | AU19: N/A | AV19: =FALSE() -> FALSE | BA19: Item | BB19: sites/ext-AonNFPIntegration/Lists/ITSM Integration InScope Inventory
A20: PnC009 | B20: Catalog Item | C20: (P&C) Opportunities | D20: Somendra S.T. | E20: 3.1 | F20: 3.1 | O20: Teri C. | Q20: Redesign | R20: In Design | S20: 46288 | W20: 46295 | AA20: N/A | AU20: N/A | AV20: =FALSE() -> FALSE | BA20: Item | BB20: sites/ext-AonNFPIntegration/Lists/ITSM Integration InScope Inventory
A21: PnC010 | B21: Catalog Item | C21: (P&C) Pathway Campaign Request | D21: Somendra S.T. | E21: 3.1 | F21: 3.1 | O21: Teri C | Q21: Redesign | R21: In Design | S21: 46288 | W21: 46295 | AA21: N/A | AU21: N/A | AV21: =FALSE() -> FALSE | BA21: Item | BB21: sites/ext-AonNFPIntegration/Lists/ITSM Integration InScope Inventory
A22: PnC011 | B22: Catalog Item | C22: (P&C) Reporting | D22: Somendra S.T. | E22: 3.1 | F22: 3.1 | O22: Teri C | Q22: Redesign | R22: In Design | S22: 46288 | W22: 46295 | AA22: N/A | AU22: N/A | AV22: =FALSE() -> FALSE | BA22: Item | BB22: sites/ext-AonNFPIntegration/Lists/ITSM Integration InScope Inventory
A23: PnC012 | B23: Catalog Item | C23: (P&C) User Report Access | D23: Somendra S.T. | E23: 3.1 | F23: 3.1 | O23: Teri C | Q23: Redesign | R23: In Design | S23: 46288 | W23: 46295 | AA23: N/A | AU23: N/A | AV23: =FALSE() -> FALSE | BA23: Item | BB23: sites/ext-AonNFPIntegration/Lists/ITSM Integration InScope Inventory
... A26: PnC015 | B26: Catalog Item | C26: (P&C) Applied P&C Applications User Request | D26: Descoped | E26: Descoped | F26: Descoped | O26: Teri C | Q26: Redesign | R26: Descoped | S26: 46288 | W26: 46295 | AA26: N/A | AU26: N/A | AV26: =FALSE() -> FALSE | BA26: Item | BB26: sites/ext-AonNFPIntegration/Lists/ITSM Integration InScope Inventory
A27: RM001 | B27: Catalog Item | C27: Create Request | D27: N/a - Descoped | E27: N/a - Descoped | F27: N/a - Descoped | N27: Create a Request for assistance | O27: Jerry Jenkins | P27: Redesign | Q27: Retire / Descoped | R27: Descoped | Z27: N/a - Descoped | AA27: Confirmed | AB27: Jerry Jenkins | AF27: 46234 | AJ27: 46241 | AK27: 46241 | AM27: Not Started | AN27: 46247 | AO27: 46247 | AQ27: Not Started | AR27: 46295 | AS27: 46295 | AU27: N/a | BA27: Item | BB27: sites/ext-AonNFPIntegration/Lists/ITSM Integration InScope Inventory
A28: RM002 | B28: Catalog Item | C28: Salesforce | D28: Sowmya | E28: 2.1 | F28: 2.1 | G28: Complete | H28: Complete | I28: In Progress | J28: Requested | N28: Create a request for Salesforce assistance. | O28: Kris Lipetsky | P28: Redesign | Q28: Redesign | R28: UAT In Progress | S28: 46255 | T28: Awaiting confirmation from Kris L. on NFP Salesforce application record (email out to Deepak B. and Simon S. on 7/7); Expected reply from Kris L. on 7/20 | U28: Kris to review current form design and provide PwC with updated design information on the Salesforce New User / Reactivate / PAM Record form | V28: STRY0147039 | W28: 46262 | Z28: July 6 | AE28: Complete | AF28: 46234 | AG28: 46234 | AI28: Complete | AJ28: 46255 | AK28: 46260 | AL28: 46260 | AM28: In Progress | AN28: 46261 | AO28: 46261 | AP28: 46265 | AQ28: Not Started | AR28: 46295 | AS28: 46295 | AU28: N/a | BA28: Item | BB28: sites/ext-AonNFPIntegration/Lists/ITSM Integration InScope Inventory
A29: RM003 | B29: Catalog Item | C29: Website Access Request | D29: Olivia | E29: 0 | F29: 0 | N29: Website Access Request | O29: Erryn Rodriguez | P29: Adopt | Q29: Adopt | R29: Adopt - No Build Needed | X29: Website Exception Request | Y29: Ajit Kumar Sharma | Z29: N/a - No design required | AE29: Complete | AF29: 46234 | AG29: 46234 | AH29: 46234 | AI29: Complete | AJ29: 46234 | AK29: 46234 | AL29: 46234 | AM29: Not Started | AN29: 46241 | AO29: 46241 | AQ29: Not Started | AR29: 46295 | AS29: 46295 | AU29: N/a | BA29: Item | BB29: sites/ext-AonNFPIntegration/Lists/ITSM Integration InScope Inventory
A30: RM004 | B30: Catalog Item | C30: NFP Financial Systems Assistance (Formally Concur) | D30: Tarun | E30: 1.2 | F30: 1.2 | G30: Complete | H30: In Progress | I30: Not Started | N30: Build new catalog item "NFP Financial Systems Assistance" to replace RM004 - Concur | O30: Bobbie Johnson | P30: Adapt | Q30: Redesign | R30: Ready for Testing | S30: 46248 | U30: Scope change confirmed 7/13 | W30: 46254 | X30: Application Generic Service Request | Y30: Simon Sankey | Z30: N/a - No follow ups from survey at this time | AA30: Confirmed | AB30: Kelly Cecchini, Nancy Govea | AE30: In Progress | AF30: 46234 | AG30: 46234 | AH30: 46234 | AI30: In Progress | AJ30: 46248 | AK30: 46254 | AL30: 46254 | AM30: In Progress | AN30: 46260 | AO30: 46260 | AQ30: Not Started | AR30: 46295 | AS30: 46295 | AU30: Available alone and in O&T OG | AV30: =TRUE() -> TRUE | BA30: Item | BB30: sites/ext-AonNFPIntegration/Lists/ITSM Integration InScope Inventory
A31: RM005 | B31: Catalog Item | C31: Remote Work Request | D31: Sowmya | E31: 1.1 | F31: 1.2 | G31: Complete | H31: Complete | I31: Not Started | J31: Not Started | K31: Not Started | L31: Not Started | M31: Not Started | N31: Create a Request to be allowed to work remotely. | O31: Jenna Davies, John Stratton | P31: Adopt | Q31: Redesign | R31: On Hold | S31: 46246 | W31: 46253 | X31: Aon Remote Access | Y31: Soumendu Kumar Singh | AA31: Confirmed | AE31: In Progress | AF31: 46234 | AG31: 46241 | AI31: Not Started | AJ31: 46248 | AK31: 46248 | AM31: Not Started | AN31: 46254 | AO31: 46254 | AQ31: Not Started | AR31: 46295 | AS31: 46295 | AU31: N/a | BA31: Item | BB31: sites/ext-AonNFPIntegration/Lists/ITSM Integration InScope Inventory
A32: RM006 | B32: Catalog Item | C32: EPIC | D32: N/a - Descoped | E32: N/a - Descoped | F32: N/a - Descoped | N32: Create a request for EPIC assistance. | O32: Teri Cote | P32: Redesign | Q32: Retire / Descoped | R32: Descoped | U32: Confirmed not needed by Teri via questionnaire email response on 25-Jun. Confirmed by Frank 7/13. | Z32: July 15 | AA32: Confirmed | AF32: 46234 | AJ32: 46255 | AK32: 46255 | AM32: Not Started | AN32: 46261 | AO32: 46261 | AQ32: Not Started | AR32: 46295 | AS32: 46295 | AU32: N/a | AV32: =TRUE() -> TRUE | BA32: Item | BB32: sites/ext-AonNFPIntegration/Lists/ITSM Integration InScope Inventory
A33: RM007 | B33: Catalog Item | C33: Onboarding and Transitions - Egnyte | D33: N/a - Descoped | E33: N/a - Descoped | F33: N/a - Descoped | N33: Create a request for Egnyte assistance | O33: Giovanni Scrima | P33: Redesign | Q33: Retire / Descoped | R33: Descoped | U33: Confirmed that Egnyte does not need to be recreated within the Onboarding & Transitions order guide. Non-onboarding related requests will route through Aon's existing intake paths; Generic Application Service Request. | Z33: July 6 | AA33: Confirmed | AF33: 46234 | AJ33: 46241 | AK33: 46241 | AM33: Not Started | AN33: 46247 | AO33: 46247 | AQ33: Not Started | AR33: 46295 | AS33: 46295 | AU33: N/a | AV33: =TRUE() -> TRUE | BA33: Item | BB33: sites/ext-AonNFPIntegration/Lists/ITSM Integration InScope Inventory
A34: RM008 | B34: Catalog Item | C34: Active Directory Orchestration | D34: Javier | E34: 1.1 | F34: 2.1 | N34: Active Directory Orchestration | O34: Antowan Jones | P34: Redesign | Q34: Redesign | R34: In Build Progress | S34: 46241 | V34: STRY0146932 | W34: 46246 | Z34: June 26 | AB34: Donald Barksdale, Antowan Jones | AE34: Complete | AF34: 46234 | AG34: 46220 | AH34: 46220 | AI34: Complete | AJ34: 46241 | AK34: 46241 | AM34: Not Started | AN34: 46247 | AO34: 46247 | AQ34: Not Started | AR34: 46295 | AS34: 46295 | AU34: Only available in O&T OG | AV34: =TRUE() -> TRUE | AX34: Yes | BA34: Item | BB34: sites/ext-AonNFPIntegration/Lists/ITSM Integration InScope Inventory
A35: RM009 | B35: Catalog Item | C35: AD Account and Mailbox/Calendar Setup Offboarding | D35: Backlog | E35: 2.2 | F35: 2.2 | N35: AD Account and Mailbox/Calendar Setup Offboarding | O35: Donald Barksdale | P35: Redesign | Q35: Redesign | R35: In Design | S35: 46258 | U35: Awaiting Scope Confirmation Changes (AD Integration) | W35: 46262 | Z35: July 7 | AB35: Donald Barksdale, Nick Pilisko, Stephanie Lujan, Michael Kruger | AE35: In Progress | AF35: 46234 | AG35: 46241 | AI35: Not Started | AJ35: 46265 | AK35: 46265 | AM35: Not Started | AN35: 46268 | AO35: 46268 | AQ35: Not Started | AR35: 46295 | AS35: 46295 | AU35: Only available in O&T OG | AV35: =TRUE() -> TRUE | AX35: Yes | BA35: Item | BB35: sites/ext-AonNFPIntegration/Lists/ITSM Integration InScope Inventory
A36: RM010 | B36: Catalog Item | C36: Request Hardware | D36: N/a - Descoped | E36: N/a - Descoped | F36: N/a - Descoped | N36: Request New Computer or Peripheral. | O36: Ethan Katz | P36: Adopt | Q36: Retire / Descoped | R36: Descoped | U36: Retire. Replaced by AON's existing "Hardware Systems and Applications Access" order guide (Hardware & Peripherals path). | X36: Hardware, Systems & Application Access | Y36: Simon Sankey | Z36: July 9 | AA36: Confirmed | AF36: 46234 | AJ36: 46255 | AK36: 46255 | AM36: Not Started | AN36: 46261 | AO36: 46261 | AQ36: Not Started | AR36: 46295 | AS36: 46295 | AU36: N/a | BA36: Item | BB36: sites/ext-AonNFPIntegration/Lists/ITSM Integration InScope Inventory
A37: RM011 | B37: Catalog Item | C37: NFP Phone System - Termination | D37: Tarun | E37: 2.1 | F37: 2.1 | N37: Backend item: NFP Phone System termination/offboarding | O37: Kim Ragland | P37: Redesign | Q37: Redesign | R37: Not Started | S37: 46251 | W37: 46258 | Z37: July 14 | AE37: In Progress | AF37: 46234 | AG37: 46234 | AI37: Not Started | AJ37: 46255 | AK37: 46255 | AM37: Not Started | AN37: 46261 | AO37: 46261 | AQ37: Not Started | AR37: 46295 | AS37: 46295 | AU37: Only available in O&T OG | AV37: =TRUE() -> TRUE | BA37: Item | BB37: sites/ext-AonNFPIntegration/Lists/ITSM Integration InScope Inventory
A38: RM012 | B38: Catalog Item | C38: Salesforce Policy Update | D38: Olivia | E38: 1.1 | F38: 1.1 | G38: Complete | H38: Complete | I38: Complete | J38: Done (08/31) | K38: Confirmed (08/31) | N38: Request to update a Salesforce policy | O38: Andrew Howard | P38: Redesign | Q38: Redesign | R38: UAT In Progress | S38: 46227 | V38: STRY0146814 | W38: 46234 | Z38: July 6 | AD38: Build shell completed - ready for test script creation Placeholders still in place for: Assignment Group, Catalog Location | AF38: 46234 | AG38: 46209 | AH38: 46209 | AI38: Complete | AJ38: 46241 | AK38: 46241 | AL38: 46230 | AM38: In Progress | AN38: 46247 | AO38: 46247 | AQ38: Not Started | AR38: 46295 | AS38: 46295 | AU38: N/a | AW38: Placeholder Assignment Group for testing | BA38: Item | BB38: sites/ext-AonNFPIntegration/Lists/ITSM Integration InScope Inventory
A39: RM013 | B39: Catalog Item | C39: AD Account and Mailbox/Calendar Setup | D39: Backlog | E39: 2.2 | F39: 2.2 | N39: AD Account and Mailbox/Calendar Setup | O39: Donald Barksdale | P39: Redesign | Q39: Redesign | R39: In Design | S39: 46258 | U39: Part of NFP On/offboarding Order Guide; Need to scope with Frank's team upon follow up with Antowan on AD integration scope. | W39: 46262 | Z39: July 7 | AB39: Donald Barksdale, Nick Pilisko, Stephanie Lujan, Michael Kruger | AE39: In Progress | AF39: 46234 | AG39: 46241 | AI39: Not Started | AJ39: 46265 | AK39: 46265 | AM39: Not Started | AN39: 46268 | AO39: 46268 | AQ39: Not Started | AR39: 46295 | AS39: 46295 | AU39: Only available in O&T OG | AV39: =TRUE() -> TRUE | AX39: Yes | BA39: Item | BB39: sites/ext-AonNFPIntegration/Lists/ITSM Integration InScope Inventory
A40: RM014 | B40: Catalog Item | C40: Financial Applications | D40: N/a - Descoped | E40: N/a - Descoped | F40: N/a - Descoped | N40: Financial Applications | O40: Tyler Webber | P40: Redesign | Q40: Retire / Descoped | R40: Descoped | U40: Part of NFP On/offboarding Order Guide; Antowan to confirm whether financial apps remain in the onboarding and transitions guide | Z40: July 13 | AF40: 46234 | AJ40: 46248 | AK40: 46248 | AM40: Not Started | AN40: 46254 | AO40: 46254 | AQ40: Not Started | AR40: 46295 | AS40: 46295 | AU40: N/a | BA40: Item | BB40: sites/ext-AonNFPIntegration/Lists/ITSM Integration InScope Inventory
A41: RM015 | B41: Catalog Item | C41: Onboarding DocuSign | D41: Olivia | E41: 1.1 | F41: 1.1 | G41: Complete | H41: Complete | I41: Complete | J41: Done (08/31) | K41: Pending | L41: Pending Impln. | M41: Pending Impln. | N41: Create a request for DocuSign assistance | O41: Tony Nicosia | P41: Redesign | Q41: Redesign | R41: UAT In Progress | S41: 46241 | U41: Part of NFP On/offboarding Order Guide | V41: STRY0146965 | W41: 46248 | Z41: July 7 | AB41: Brian English, Tony Nicosia | AE41: Complete | AF41: 46234 | AG41: 46213 | AH41: 46213 | AI41: Complete | AJ41: 46241 | AK41: 46241 | AL41: 46241 | AM41: In Progress | AN41: 46247 | AO41: 46247 | AQ41: Not Started | AR41: 46295 | AS41: 46295 | AU41: Available alone and in O&T OG | AV41: =TRUE() -> TRUE | AW41: Assignment Group - confirm what it should be during UAT, Order Guide Linkage | AX41: Yes | BA41: Item | BB41: sites/ext-AonNFPIntegration/Lists/ITSM Integration InScope Inventory
A42: RM016 | B42: Catalog Item | C42: OneDrive Access | D42: Olivia | E42: 1.2 | F42: 1.2 | G42: Complete | H42: Complete | I42: Not Started | J42: Not Started | K42: Not Started | N42: OneDrive Access | O42: Brian English | P42: Adopt | Q42: Redesign | R42: Ready for Testing | S42: 46248 | U42: Original disposition: Adopt (assumed Aon's existing OneDrive access request would cover NFP needs) Updated disposition: Redesign, A standalone NFP OneDrive catalog item is needed, separate from Aon's, since users are on a dual tenant and some staff will need both Aon and NFP OneDrive access. Confirmed details: No automation/integrations tied to this request access is granted manually through manager approval. Fulfilled by Brian's SharePoint team; this assignment group will carry over to the Aon environment. Next step: Disposition change (adopt to redesign) will be documented in the scope change log. | V42: STRY0147007 | W42: 46255 | X42: Hardware, Systems & Application Access | Y42: Simon Sankey | Z42: Application Related? | AE42: Complete | AF42: 46234 | AG42: 46213 | AH42: 46213 | AI42: Complete | AJ42: 46248 | AK42: 46248 | AL42: 46248 | AM42: Not Started | AN42: 46254 | AO42: 46254 | AQ42: Not Started | AR42: 46295 | AS42: 46295 | AU42: Only available in O&T OG | AV42: =TRUE() -> TRUE | AW42: TIMERS are INCORRECT - shortened for testing purposes only. | AX42: Yes | BA42: Item | BB42: sites/ext-AonNFPIntegration/Lists/ITSM Integration InScope Inventory
A43: RM017 | B43: Catalog Item | C43: Open Path | D43: Sowmya | E43: 1.1 | F43: 1.2 | G43: Complete | H43: Complete | I43: In Progress | N43: Provides access to physical locations. | O43: Anthony Papandrea | P43: Redesign | Q43: Redesign | R43: Ready for Testing | S43: 46246 | W43: 46253 | Z43: July 9 | AB43: Chris Derico, Anthony Papandrea | AE43: Complete | AF43: 46234 | AG43: 46220 | AH43: 46220 | AI43: Not Started | AJ43: 46248 | AK43: 46248 | AM43: Not Started | AN43: 46254 | AO43: 46254 | AQ43: Not Started | AR43: 46295 | AS43: 46295 | AU43: Only available in O&T OG | AV43: =TRUE() -> TRUE | AX43: Yes | BA43: Item | BB43: sites/ext-AonNFPIntegration/Lists/ITSM Integration InScope Inventory
A44: RM018 | B44: Catalog Item | C44: Epic Access Form | D44: N/a - Descoped | E44: N/a - Descoped | F44: N/a - Descoped | N44: Form to update user roles for the application EPIC. | O44: Teri Cote | P44: Redesign | Q44: Retire / Descoped | R44: Descoped | U44: Confirmed not needed by Teri via questionnaire email response on 25-Jun. Confirmed by Frank 7/13. | Z44: July 15 | AA44: Confirmed | AF44: 46234 | AJ44: 46255 | AK44: 46255 | AM44: Not Started | AN44: 46261 | AO44: 46261 | AQ44: Not Started | AR44: 46295 | AS44: 46295 | AU44: N/a | BA44: Item | BB44: sites/ext-AonNFPIntegration/Lists/ITSM Integration InScope Inventory
A45: RM019 | B45: Catalog Item | C45: Adobe Pro | D45: Olivia | E45: 1.1 | F45: 1.1 | G45: Complete | H45: Complete | I45: Complete | J45: Done (08/31) | K45: Pending | L45: Pending Impln. | M45: Pending Impln. | N45: Create a request for Adobe Pro assistance. | O45: Tony Nicosia | P45: Adapt | Q45: Redesign | R45: UAT In Progress | S45: 46234 | U45: Updated disposition: Redesign, Adobe Pro will not be loaded into Aon's Application Portfolio Management (APM) database, so it won't appear in the generic application request item; a standalone catalog item is needed. Confirmed details: Two distinct needs identified: (1) new license requests, (2) troubleshooting/support for existing licenses. An automated ticket-generation function exists on the onboarding form (chatbox logic based on yes/no license selection) and Brian flagged this may mean two catalog items already exist; To be confirmed by PwC team. Fulfillment: Requests go directly to Brian, with Tony as backup. Team naming decision: Rather than creating dedicated "Adobe Pro" group both will roll under the existing email systems group (Brian + Tony), avoiding group sprawl. | V45: STRY0146842 | W45: 46241 | X45: Application Generic Service Request | Y45: John Edridge, Simon Sankey | AA45: Confirmed | AB45: Brian English, Tony Nicosia | AE45: Complete | AF45: 46234 | AG45: 46211 | AH45: 46211 | AI45: Complete | AJ45: 46241 | AK45: 46241 | AL45: 46238 | AM45: In Progress | AN45: 46247 | AO45: 46247 | AQ45: Not Started | AR45: 46295 | AS45: 46295 | AU45: N/a | AV45: =FALSE() -> FALSE | AW45: Placeholder Assignment Group for testing | AX45: Yes | BA45: Item | BB45: sites/ext-AonNFPIntegration/Lists/ITSM Integration InScope Inventory
A46: RM020 | B46: Catalog Item | C46: Microsoft Teams | D46: Olivia | E46: 1.1 | F46: 1.1 | G46: Complete | H46: Complete | I46: Complete | J46: Done (09/01) | K46: Done (09/01) | L46: Pending Impln. | M46: Pending Impln. | N46: Microsoft Teams | O46: Srikanth Komirishetty | P46: Redesign | Q46: Redesign | R46: UAT In Progress | S46: 46239 | U46: Part of NFP On/offboarding Order Guide | V46: STRY0146964 | W46: 46246 | AB46: Brian English | AE46: Complete | AF46: 46234 | AG46: 46213 | AH46: 46213 | AI46: Complete | AJ46: 46241 | AK46: 46241 | AL46: 46241 | AM46: In Progress | AN46: 46247 | AO46: 46247 | AQ46: Not Started | AR46: 46295 | AS46: 46295 | AU46: Only available in O&T OG | AV46: =TRUE() -> TRUE | AX46: Yes | BA46: Item | BB46: sites/ext-AonNFPIntegration/Lists/ITSM Integration InScope Inventory
A47: RM021 | B47: Catalog Item | C47: New Copilot Request | D47: N/a - Descoped | E47: N/a - Descoped | F47: N/a - Descoped | O47: James (Jim) Rossi | P47: Adopt | Q47: Retire / Descoped | R47: Descoped | U47: Confirmed by Frank 7/13 | X47: Hardware, Systems & Application Access | Y47: Simon Sankey | AA47: Confirmed | AF47: 46234 | AJ47: 46255 | AK47: 46255 | AM47: Not Started | AN47: 46261 | AO47: 46261 | AQ47: Not Started | AR47: 46295 | AS47: 46295 | AU47: N/a | BA47: Item | BB47: sites/ext-AonNFPIntegration/Lists/ITSM Integration InScope Inventory
A48: RM022 | B48: Catalog Item | C48: NFP Phone System | D48: Tarun | E48: 2.1 | F48: 2.1 | N48: Request new NFP Phone System access | O48: Kim Ragland | P48: Adopt | Q48: Redesign | R48: Not Started | S48: 46251 | U48: Move to Redesign? | W48: 46258 | X48: Phone Services Request | Y48: Joe Nalio | Z48: July 14 | AE48: In Progress | AF48: 46234 | AG48: 46234 | AI48: Not Started | AJ48: 46255 | AK48: 46255 | AM48: Not Started | AN48: 46261 | AO48: 46261 | AQ48: Not Started | AR48: 46295 | AS48: 46295 | AU48: Available alone and in O&T OG | AV48: =TRUE() -> TRUE | BA48: Item | BB48: sites/ext-AonNFPIntegration/Lists/ITSM Integration InScope Inventory
A49: RM023 | B49: Catalog Item | C49: Virtual Computer, VDI, or CloudPC (For accessing firm specific applications) | D49: Javier | E49: 1.1 | F49: 1.1 | G49: Complete | H49: Complete | I49: Complete | J49: Done (08/31) | K49: Pending | N49: Virtual Hardware | O49: Dion Mohammed | P49: Redesign | Q49: Redesign | R49: UAT In Progress | S49: 46241 | U49: Part of NFP On/offboarding Order Guide this development holds a dependency for a custom table called u_business_lines, Finally the custom table was replaced by sys_choice table, crating the 25 items directly in prod and moved down to test and dev | W49: 46246 | Z49: N/a - No follow up required from survey | AB49: Steve Prodanovski, David Rossi | AE49: Complete | AF49: 46234 | AG49: 46220 | AH49: 46220 | AI49: Complete | AJ49: 46241 | AK49: 46241 | AL49: 46241 | AM49: In Progress | AN49: 46253 | AO49: 46255 | AQ49: Not Started | AR49: 46295 | AS49: 46295 | AU49: Only available in O&T OG | AV49: =TRUE() -> TRUE | AX49: Yes | BA49: Item | BB49: sites/ext-AonNFPIntegration/Lists/ITSM Integration InScope Inventory
A50: RM024 | B50: Catalog Item | C50: Plan Document Request | D50: Olivia | E50: 1.1 | F50: 1.1 | G50: Complete | H50: Complete | I50: Complete | J50: Done (08/31) | N50: Request Plan Document Package For Clients | O50: Chase Cannon | P50: Redesign | Q50: Redesign | R50: UAT In Progress | S50: 46227 | V50: STRY0146745 | W50: 46234 | Z50: N/a - no follow ups required from survey | AB50: Shawna Cochran, Chase Cannon | AD50: Build shell completed - ready for test script creation Placeholders still in place for: Assignment Group, Catalog Location | AE50: Complete | AF50: 46234 | AG50: 46203 | AH50: 46203 | AI50: Complete | AJ50: 46241 | AK50: 46241 | AL50: 46230 | AM50: In Progress | AN50: 46247 | AO50: 46247 | AQ50: Not Started | AR50: 46295 | AS50: 46295 | AU50: N/a | AW50: Placeholder Assignment Group for testing | BA50: Item | BB50: sites/ext-AonNFPIntegration/Lists/ITSM Integration InScope Inventory
A51: RM025 | B51: Catalog Item | C51: Applied Epic | D51: N/a - Descoped | E51: N/a - Descoped | F51: N/a - Descoped | N51: Create Request for Applied Epic Assistance | O51: Teri Cote | P51: Redesign | Q51: Retire / Descoped | R51: Descoped | U51: Scope change confirmed 7/13 by Frank. | Z51: July 15 | AA51: Confirmed | AF51: 46234 | AJ51: 46248 | AK51: 46248 | AM51: Not Started | AN51: 46254 | AO51: 46254 | AQ51: Not Started | AR51: 46295 | AS51: 46295 | AU51: N/a | BA51: Item | BB51: sites/ext-AonNFPIntegration/Lists/ITSM Integration InScope Inventory
A52: RM026 | B52: Catalog Item | C52: AVID | D52: N/a - Descoped | E52: N/a - Descoped | F52: N/a - Descoped | N52: Create a request for AVID assistance. | O52: Bobbie Johnson | P52: Adapt | Q52: Retire / Descoped | R52: Descoped | X52: Application Generic Service Request | Y52: John Edridge, Simon Sankey | Z52: N/a - Descoped | AA52: Confirmed | AF52: 46234 | AJ52: 46255 | AK52: 46255 | AM52: Not Started | AN52: 46261 | AO52: 46261 | AQ52: Not Started | AR52: 46295 | AS52: 46295 | AU52: N/a | BA52: Item | BB52: sites/ext-AonNFPIntegration/Lists/ITSM Integration InScope Inventory
A53: RM027 | B53: Catalog Item | C53: LastPass | D53: Olivia | E53: 1.2 | F53: 1.2 | G53: Complete | H53: Complete | I53: Not Started | J53: Not Started | K53: Not Started | N53: LastPass | O53: Giovanni Scrima | P53: Redesign | Q53: Redesign | R53: Ready for Testing | S53: 46248 | U53: Part of NFP On/offboarding Order Guide | V53: STRY0147008 | W53: 46255 | Z53: July 6 | AE53: Complete | AF53: 46234 | AG53: 46213 | AH53: 46213 | AI53: Complete | AJ53: 46248 | AK53: 46248 | AL53: 46248 | AM53: Not Started | AN53: 46254 | AO53: 46254 | AQ53: Not Started | AR53: 46295 | AS53: 46295 | AU53: Only available in O&T OG | AV53: =TRUE() -> TRUE | AX53: Yes | BA53: Item | BB53: sites/ext-AonNFPIntegration/Lists/ITSM Integration InScope Inventory
A54: RM028 | B54: Catalog Item | C54: Strategic Ledger (SL Value) Addition | D54: Tarun | E54: 1.2 | F54: 1.2 | G54: Complete | H54: On Hold | N54: Create Strategic Ledger (SL) values for financial tagging | O54: Kelly Cecchini | P54: Redesign | Q54: Redesign | R54: Ready for Testing | S54: 46248 | W54: 46254 | Z54: July 13 | AE54: Complete | AF54: 46234 | AG54: 46234 | AH54: 46234 | AI54: Complete | AJ54: 46248 | AK54: 46266 | AL54: 46266 | AM54: Not Started | AN54: 46260 | AO54: 46260 | AQ54: Not Started | AR54: 46295 | AS54: 46295 | AU54: N/a | BA54: Item | BB54: sites/ext-AonNFPIntegration/Lists/ITSM Integration InScope Inventory
A55: RM029 | B55: Catalog Item | C55: P&C Applications User Request | D55: Tarun | E55: 1.1 | F55: 1.2 | G55: Complete | H55: In Progress | N55: Request new P&C application user (HR-submitted) | O55: Teri Cote | P55: Redesign | Q55: Redesign | R55: In Build Progress | S55: 46256 | W55: 46258 | Z55: July 15 | AE55: Complete | AF55: 46241 | AG55: 46241 | AH55: 46241 | AI55: In Progress | AJ55: 46248 | AK55: 46256 | AM55: Not Started | AN55: 46260 | AO55: 46262 | AQ55: Not Started | AR55: 46295 | AS55: 46295 | AU55: N/a | AX55: Yes | BA55: Item | BB55: sites/ext-AonNFPIntegration/Lists/ITSM Integration InScope Inventory
A56: RM030 | B56: Catalog Item | C56: Carrier Statement Mass Delete Request | D56: Javier | E56: 1.1 | F56: 1.1 | G56: Complete | H56: Complete | I56: In Progress | J56: Not Started | K56: Not Started | N56: Statement Mass Delete Request | O56: Kris Lipetsky | P56: Redesign | Q56: Redesign | R56: UAT In Progress | S56: 46241 | V56: STRY0146627 | W56: 46246 | AE56: Complete | AF56: 46234 | AG56: 46219 | AH56: 46219 | AI56: Complete | AJ56: 46241 | AK56: 46216 | AL56: 46216 | AM56: In Progress | AN56: 46253 | AO56: 46255 | AP56: 46255 | AQ56: Not Started | AR56: 46295 | AS56: 46295 | AU56: N/a | BA56: Item | BB56: sites/ext-AonNFPIntegration/Lists/ITSM Integration InScope Inventory
A57: RM031 | B57: Catalog Item | C57: NFP DevOps Support | D57: Tarun | E57: 1.1 | F57: 1.1 | G57: Complete | H57: Complete | I57: In Progress | J57: Not Started | K57: Not Started | N57: Build and configure NFP DevOps Support catalog item (RM031) in Aon ServiceNow, including rename from "Release Management Support Request" and Request Type choice list update | O57: Frank Natividad | P57: Redesign | Q57: Redesign | R57: Ready for Testing | S57: 46234 | U57: Rename to 'NFP DevOps Support' | V57: STRY0146752 | W57: 46241 | Z57: July 10 | AE57: Complete | AF57: 46234 | AG57: 46213 | AH57: 46213 | AI57: Complete | AJ57: 46241 | AK57: 46241 | AL57: 46241 | AM57: In Progress | AN57: 46247 | AO57: 46261 | AQ57: Not Started | AR57: 46295 | AS57: 46295 | AU57: N/a | BA57: Item | BB57: sites/ext-AonNFPIntegration/Lists/ITSM Integration InScope Inventory
A58: RM032 | B58: Catalog Item | C58: Salesforce New User Request | D58: Sowmya | E58: 2.1 | F58: 2.1 | G58: Complete | H58: Complete | I58: In Progress | J58: Requested | N58: This form is used to add a new user to the Salesforce CRM platform and must be submitted/approved by the user's manager or Regional Salesforce Champion. | O58: Kris Lipetsky | P58: Redesign | Q58: Redesign | R58: UAT In Progress | S58: 46255 | T58: Awaiting design decisions from Kris L.; Action item on Kris to provide the information by 7/13, email reminder sent on 7/13 requesting the information | V58: STRY0147039 | W58: 46262 | Z58: July 6 | AE58: Complete | AF58: 46234 | AG58: 46234 | AI58: Complete | AJ58: 46255 | AK58: 46260 | AL58: 46260 | AM58: In Progress | AN58: 46261 | AO58: 46261 | AP58: 46265 | AQ58: Not Started | AR58: 46295 | AS58: 46295 | AU58: N/a | BA58: Item | BB58: sites/ext-AonNFPIntegration/Lists/ITSM Integration InScope Inventory
A59: RM033 | B59: Catalog Item | C59: Compliance Due Diligence Questionnaire/RFP Request | D59: Sowmya | E59: 2.2 | F59: 2.2 | G59: In Progress | H59: Not Started | I59: Not Started | N59: Requests for help completing due diligence questionnaires, requests for proposals (RFPs), and similar. | O59: Trent Reynolds | P59: Redesign | Q59: Redesign | R59: In Design | S59: 46262 | U59: pending NFP/Aon form reconciliation (targeted end of next week) and finalized design/target group/catalog placement delivered before the July 31 design cutoff, otherwise it will proceed with the current-state design as-is | W59: 46269 | Z59: July 8 | AE59: In Progress | AF59: 46234 | AG59: 46234 | AI59: Not Started | AJ59: 46265 | AK59: 46265 | AM59: Not Started | AN59: 46268 | AO59: 46268 | AQ59: Not Started | AR59: 46295 | AS59: 46295 | AU59: N/a | BA59: Item | BB59: sites/ext-AonNFPIntegration/Lists/ITSM Integration InScope Inventory
A60: RM034 | B60: Catalog Item | C60: Financial Systems Security Request Form - Regional Offices | D60: Sowmya | E60: 2.2 | F60: 2.2 | G60: In Progress | H60: Not Started | I60: Not Started | N60: Request form for financial systems security for regional offices | O60: Tyler Webber | P60: Redesign | Q60: Redesign | R60: In Design | S60: 46262 | T60: Availability of approval data in Aon's ServiceNow required to be investigated (PwC to follow up). | U60: PwC to confirm cost center data & Need confirmation on concur, powerbi, data warehouse, 606 reporting, and blackline with respective owners | W60: 46269 | Z60: July 13 | AE60: In Progress | AF60: 46234 | AG60: 46241 | AI60: Not Started | AJ60: 46265 | AK60: 46265 | AM60: Not Started | AN60: 46268 | AO60: 46268 | AQ60: Not Started | AR60: 46295 | AS60: 46295 | AU60: Available alone and in O&T OG | AV60: =TRUE() -> TRUE | AX60: Yes | BA60: Item | BB60: sites/ext-AonNFPIntegration/Lists/ITSM Integration InScope Inventory
A61: RM035 | B61: Catalog Item | C61: Return from LOA | D61: Javier | E61: 1.2 | F61: 1.2 | N61: Leave of Absence Reinstatement | O61: Antowan Jones | P61: Adopt | Q61: Redesign | R61: Ready for Build | S61: 46269 | U61: Scope change confirmed 7/13 - as-is re-creation from NFP | V61: STRY0147195 | W61: 46276 | X61: Leave of Absence (Return from Leave sub-type) | Y61: Anca Dobrescu | Z61: June 26 | AA61: Confirmed | AE61: Complete | AF61: 46234 | AG61: 46216 | AH61: 46216 | AI61: Not Started | AJ61: 46248 | AK61: 46248 | AM61: Not Started | AN61: 46254 | AO61: 46254 | AQ61: Not Started | AR61: 46295 | AS61: 46295 | AU61: Only available in O&T OG | AV61: =TRUE() -> TRUE | AX61: Yes | BA61: Item | BB61: sites/ext-AonNFPIntegration/Lists/ITSM Integration InScope Inventory
A62: RM036 | B62: Catalog Item | C62: New Software Approval Request | D62: Javier | E62: 1.2 | F62: 1.2 | N62: New Software Package Request | O62: Andy Goss | P62: Adopt | Q62: Adapt | R62: In Design | S62: 46269 | V62: STRY0147196 | W62: 46276 | X62: Application Packaging Request | Y62: Sanman Parvalkar | AA62: Confirmed | AE62: In Progress | AF62: 46234 | AG62: 46241 | AI62: Not Started | AJ62: 46248 | AK62: 46248 | AM62: Not Started | AN62: 46254 | AO62: 46254 | AQ62: Not Started | AR62: 46295 | AS62: 46295 | AU62: N/a | BA62: Item | BB62: sites/ext-AonNFPIntegration/Lists/ITSM Integration InScope Inventory
A63: RM037 | B63: Catalog Item | C63: Go Anywhere Request | D63: Tarun | E63: 1.2 | F63: 1.2 | G63: Complete | H63: Complete | I63: Complete | N63: For file transfers and additional file processing. | O63: Enoch Tong | P63: Redesign | Q63: Adapt | R63: Ready for Testing | S63: 46248 | U63: Awaiting design confirmation via email | V63: STRY0147029 | W63: 46255 | AE63: Complete | AF63: 46234 | AG63: 46234 | AH63: 46234 | AI63: Complete | AJ63: 46248 | AK63: 46258 | AL63: 46258 | AM63: Not Started | AN63: 46260 | AO63: 46261 | AP63: 46261 | AQ63: Not Started | AR63: 46295 | AS63: 46295 | AU63: N/a | AX63: Yes | BA63: Item | BB63: sites/ext-AonNFPIntegration/Lists/ITSM Integration InScope Inventory
A64: RM038 | B64: Catalog Item | C64: Online Banking Request Form | D64: Sowmya | E64: 1.2 | F64: 1.2 | G64: Complete | H64: Complete | I64: In Progress | J64: Requested | K64: Not Started | L64: Not Started | M64: Not Started | N64: Create a request for online banking through the Wells Fargo system. | O64: Eugene Likhterman | P64: Redesign | Q64: Redesign | R64: Ready for Testing | S64: 46248 | U64: will be connecting with Brian wagner, to discuss on KB article download feature for catalog item | V64: STRY0146862 | W64: 46255 | Z64: N/a - No follow ups from survey required | AE64: Complete | AF64: 46234 | AG64: 46185 | AH64: 46185 | AI64: Complete | AJ64: 46248 | AK64: 46248 | AL64: 46251 | AM64: Not Started | AN64: 46254 | AO64: 46254 | AQ64: Not Started | AR64: 46295 | AS64: 46295 | AU64: N/a | BA64: Item | BB64: sites/ext-AonNFPIntegration/Lists/ITSM Integration InScope Inventory
A65: RM039 | B65: Catalog Item | C65: Name/Email Change Request | D65: Javier | E65: 1.1 | F65: 1.1 | G65: Complete | H65: Complete | I65: Complete | J65: Done (08/31) | K65: Done (09/01) | N65: Form for an employee name and/or email change request. Note: HR must verify employee has provided the required identification documentation before submission. | O65: Antowan Jones | P65: Redesign | Q65: Redesign | R65: UAT In Progress | S65: 46241 | V65: STRY0146875 | W65: 46246 | Z65: June 26 | AB65: Antowan Jones | AE65: Complete | AF65: 46234 | AG65: 46220 | AH65: 46220 | AI65: Complete | AJ65: 46241 | AK65: 46240 | AL65: 46240 | AM65: In Progress | AN65: 46253 | AO65: 46259 | AP65: 46259 | AQ65: Not Started | AR65: 46295 | AS65: 46295 | AU65: Available alone and in O&T OG | AV65: =TRUE() -> TRUE | AX65: Yes | BA65: Item | BB65: sites/ext-AonNFPIntegration/Lists/ITSM Integration InScope Inventory
A66: RM040 | B66: Catalog Item | C66: Integrations Hardware Request | D66: Backlog | E66: 2.2 | F66: 2.2 | N66: Request Hardware for Integrations | O66: Ethan Katz | P66: Adopt | Q66: Redesign | R66: In Design | S66: 46262 | T66: Awaiting follow-up meeting with NFP & Aon hardware management team; Scheduled for week of 7/13 | U66: Conversation is needed regarding CDW with Aon before finalizing this disposition | W66: 46269 | X66: Hardware, Systems & Application Access | Y66: Simon Sankey | Z66: July 9 | AA66: Confirmed | AE66: In Progress | AF66: 46234 | AG66: 46234 | AI66: Not Started | AJ66: 46265 | AK66: 46265 | AM66: Not Started | AN66: 46268 | AO66: 46268 | AQ66: Not Started | AR66: 46295 | AS66: 46295 | AU66: N/a | BA66: Item | BB66: sites/ext-AonNFPIntegration/Lists/ITSM Integration InScope Inventory
A67: RM041 | B67: Catalog Item | C67: Time Tracker | D67: Olivia | E67: 1.1 | F67: 1.1 | G67: Complete | H67: Complete | I67: Complete | J67: Not Started | K67: Not Started | N67: Application used to record time allocations. | O67: Kirk Oswalt | P67: Adopt | Q67: Redesign | R67: UAT In Progress | S67: 46234 | U67: Awaiting design confirmation via email | V67: STRY0146939 | W67: 46241 | X67: Application Generic Service Request | Y67: John Edridge, Simon Sankey | Z67: Application Related | AA67: Confirmed | AE67: Complete | AF67: 46234 | AG67: 46234 | AH67: 46233 | AI67: Complete | AJ67: 46241 | AK67: 46241 | AL67: 46241 | AM67: In Progress | AN67: 46247 | AO67: 46247 | AQ67: Not Started | AU67: Only available in O&T OG | AV67: =TRUE() -> TRUE | AW67: Placeholder Assignment Group for testing | BA67: Item | BB67: sites/ext-AonNFPIntegration/Lists/ITSM Integration InScope Inventory
A68: RM042 | B68: Catalog Item | C68: DocuSign | D68: N/a - Descoped | E68: N/a - Descoped | F68: N/a - Descoped | N68: Create a request for DocuSign assistance | O68: Brian English | P68: Adopt | Q68: Retire / Descoped | R68: Descoped | X68: Docusign Access Request | Y68: Matt Ollar | Z68: July 7 | AF68: 46234 | AJ68: 46248 | AK68: 46248 | AM68: Not Started | AN68: 46254 | AO68: 46254 | AQ68: Not Started | AR68: 46295 | AS68: 46295 | AU68: N/a | BA68: Item | BB68: sites/ext-AonNFPIntegration/Lists/ITSM Integration InScope Inventory
A69: RM043 | B69: Catalog Item | C69: Producer Termination Request Form | D69: Sowmya | E69: 2.2 | F69: 2.2 | G69: Complete | H69: Complete | I69: In Progress | N69: Producer Termination Request Form | O69: Stephen Robertson | P69: Redesign | Q69: Redesign | R69: UAT In Progress | S69: 46260 | U69: May be able to be combined with Producer Additions form | V69: STRY0147163 | W69: 46262 | Z69: July 15 | AB69: sohang.thakkar@nfp.com, stephen.robertson@nfp.com | AE69: Complete | AF69: 46234 | AG69: 46234 | AH69: 46261 | AI69: Complete | AJ69: 46265 | AK69: 46265 | AL69: 46265 | AM69: In Progress | AN69: 46268 | AO69: 46268 | AP69: 46269 | AQ69: Not Started | AR69: 46295 | AS69: 46295 | AU69: N/a | BA69: Item | BB69: sites/ext-AonNFPIntegration/Lists/ITSM Integration InScope Inventory
A70: RM044 | B70: Catalog Item | C70: Financial Systems Security Request Form - Corporate Offices | D70: Sowmya | E70: 2.2 | F70: 2.2 | G70: In Progress | H70: Not Started | I70: Not Started | N70: Request form for financial systems security for corporate offices | O70: Tyler Webber | P70: Redesign | Q70: Adapt | R70: In Design | S70: 46262 | T70: Availability of approval data in Aon's ServiceNow required to be investigated (PwC to follow up). | U70: Need confirmation on concur, powerbi, data warehouse, 606 reporting, and blackline with respective owners | W70: 46269 | Z70: July 13 | AE70: In Progress | AF70: 46234 | AG70: 46241 | AI70: Not Started | AJ70: 46265 | AK70: 46265 | AM70: Not Started | AN70: 46268 | AO70: 46268 | AQ70: Not Started | AR70: 46295 | AS70: 46295 | AU70: Available alone and in O&T OG | AV70: =TRUE() -> TRUE | AX70: Yes | BA70: Item | BB70: sites/ext-AonNFPIntegration/Lists/ITSM Integration InScope Inventory
A71: RM045 | B71: Catalog Item | C71: NFP Connect Assistance | D71: Javier | E71: 1.1 | F71: 1.2 | G71: Complete | H71: Complete | I71: Complete | J71: Done | K71: Complete | N71: This form is for the software "NFP Connect", not for connectivity issues. Please call the NFP Service Desk at (212) 301-1111 for assistance with connectivity issues. | O71: Shashank Karanje | P71: Redesign | Q71: Redesign | R71: UAT In Progress | S71: 46241 | T71: Awaiting on client's direction on Custom Field development | W71: 46246 | Z71: Combined w Integrations Discussion | AB71: KamalNath Mudigati and Maheswari Padmanabha | AE71: Complete | AF71: 46234 | AG71: 46227 | AH71: 46227 | AI71: In Progress | AJ71: 46241 | AK71: 46259 | AM71: In Progress | AN71: 46260 | AO71: 46262 | AQ71: Not Started | AR71: 46295 | AS71: 46295 | AU71: N/a | BA71: Item | BB71: sites/ext-AonNFPIntegration/Lists/ITSM Integration InScope Inventory
A72: RM046 | B72: Catalog Item | C72: Inform+Equip | D72: Tarun | E72: 1.2 | F72: 1.2 | G72: Complete | H72: In Progress | N72: Onboarding/offboarding requests for Inform+Equip | O72: Tom Kirkland | P72: Redesign | Q72: Redesign | R72: In Design | S72: 46248 | U72: Part of NFP On/offboarding Order Guide | W72: 46254 | AF72: 46234 | AG72: 46234 | AH72: 46234 | AI72: In Progress | AJ72: 46248 | AK72: 46255 | AL72: 46255 | AM72: Not Started | AN72: 46260 | AO72: 46260 | AQ72: Not Started | AR72: 46295 | AS72: 46295 | AU72: Only available in O&T OG | AV72: =TRUE() -> TRUE | AX72: Yes | BA72: Item | BB72: sites/ext-AonNFPIntegration/Lists/ITSM Integration InScope Inventory
A73: RM047 | B73: Catalog Item | C73: Request New Shared Mailbox | D73: Backlog | E73: 2.2 | F73: 2.2 | N73: Create request for a new shared mailbox. | O73: Donald Barksdale | P73: Adopt | Q73: Redesign | R73: On Hold | S73: 46258 | T73: Confirmation needed on future-state fulfillment path; Discussed with Donald, Eleanor, & Frank week of 7/13 & open email thread with IAM / Messaging team from 7/7, followed up on 7/17. | W73: 46262 | X73: Create New Shared Mailbox | Y73: Soumendu Kumar Singh | Z73: July 7 | AB73: • Donald Barksdale • Nick Pilisko • Stephanie Lujan • Michael Kruger | AE73: In Progress | AF73: 46234 | AG73: 46241 | AI73: Not Started | AJ73: 46265 | AK73: 46265 | AM73: Not Started | AN73: 46268 | AO73: 46268 | AQ73: Not Started | AR73: 46295 | AS73: 46295 | AU73: N/a | AX73: Yes | BA73: Item | BB73: sites/ext-AonNFPIntegration/Lists/ITSM Integration InScope Inventory
A74: RM048 | B74: Catalog Item | C74: USB Exceptions Request | D74: Javier | E74: 1.2 | F74: 1.2 | N74: Please provide the following details | O74: John Stratton | P74: Adopt | Q74: Adapt | R74: In Design | S74: 46269 | T74: Awaiting confirmation from Tim L. (Aon) on the proposed approach; Original email sent 7/8, followed up on 7/10. | U74: Open items: (1) audit trail for approvals happening in one system but implemented in another, (2) validating identity/UPN mapping with a standard user, (3) a leadership decision on Active Directory/Intune consolidation timeline. | V74: STRY0147197 | W74: 46276 | X74: USB Access and BitLocker Encryption Exception Request | Y74: Joe Woods | Z74: Awaiting Disposition Confirmation | AE74: In Progress | AF74: 46234 | AG74: 46241 | AI74: Not Started | AJ74: 46248 | AK74: 46248 | AM74: Not Started | AN74: 46254 | AO74: 46254 | AQ74: Not Started | AR74: 46295 | AS74: 46295 | AU74: N/a | BA74: Item | BB74: sites/ext-AonNFPIntegration/Lists/ITSM Integration InScope Inventory
A75: RM049 | B75: Catalog Item | C75: Request for E-Waste Pickup | D75: N/a - Descoped | E75: N/a - Descoped | F75: N/a - Descoped | N75: Request for E-Waste Pickup | O75: Ethan Katz | P75: Redesign | Q75: Retire / Descoped | R75: Descoped | U75: Retire. Adopt AON's e-waste process as-is. | Z75: July 9 | AF75: 46234 | AJ75: 46241 | AK75: 46241 | AM75: Not Started | AN75: 46247 | AO75: 46247 | AQ75: Not Started | AR75: 46295 | AS75: 46295 | AU75: N/a | BA75: Item | BB75: sites/ext-AonNFPIntegration/Lists/ITSM Integration InScope Inventory
A76: RM050 | B76: Catalog Item | C76: Power Platform | D76: N/a - Descoped | E76: N/a - Descoped | F76: N/a - Descoped | N76: Request for PowerBI, Power Automate, and PowerApps | O76: James (Jim) Rossi | P76: Adapt | Q76: Retire / Descoped | R76: Descoped | U76: Awaiting Scope Confirmation Changes | X76: Application Generic Service Request | Y76: John Edridge, Simon Sankey | AA76: Confirmed | AF76: 46234 | AJ76: 46255 | AK76: 46255 | AM76: Not Started | AN76: 46261 | AO76: 46261 | AQ76: Not Started | AR76: 46295 | AS76: 46295 | AU76: N/a | BA76: Item | BB76: sites/ext-AonNFPIntegration/Lists/ITSM Integration InScope Inventory
A77: RM051 | B77: Catalog Item | C77: Producer Additions | D77: Sowmya | E77: 2.2 | F77: 2.2 | G77: Complete | H77: Complete | I77: In Progress | N77: Producer Additions | O77: Sohang Thakkar | P77: Redesign | Q77: Redesign | R77: UAT In Progress | S77: 46260 | U77: May be able to be combined with Producer Terminations form | V77: STRY0147163 | W77: 46262 | Z77: July 15 | AB77: stephen.robertson@nfp.com, sohang.thakkar@nfp.com | AE77: Complete | AF77: 46234 | AG77: 46234 | AH77: 46261 | AI77: Complete | AJ77: 46265 | AK77: 46265 | AL77: 46265 | AM77: In Progress | AN77: 46268 | AO77: 46268 | AQ77: Not Started | AR77: 46295 | AS77: 46295 | AU77: N/a | BA77: Item | BB77: sites/ext-AonNFPIntegration/Lists/ITSM Integration InScope Inventory
A78: RM052 | B78: Catalog Item | C78: Create New Site Code | D78: Javier | E78: 1.1 | F78: 1.1 | G78: Complete | H78: Complete | I78: Complete | J78: Done (08/31) | K78: Pending | L78: Pending Impln. | M78: Pending Impln. | N78: Create a new, non-integrated site code. | O78: Robert Spadaro | P78: Redesign | Q78: Redesign | R78: UAT In Progress | S78: 46241 | V78: STRY0146629 | W78: 46246 | Z78: June 25 | AB78: Ethan Kats Robert Spadaro | AE78: Complete | AF78: 46234 | AG78: 46216 | AH78: 46216 | AI78: Complete | AJ78: 46241 | AK78: 46220 | AL78: 46220 | AM78: In Progress | AN78: 46253 | AO78: 46255 | AP78: 46255 | AQ78: Not Started | AR78: 46295 | AS78: 46295 | AT78: 46295 | AU78: N/a | AX78: Yes | BA78: Item | BB78: sites/ext-AonNFPIntegration/Lists/ITSM Integration InScope Inventory
A79: RM053 | B79: Catalog Item | C79: PartnersFinancial Onboarding/Offboarding | D79: Javier | E79: 1.2 | F79: 1.2 | O79: Antowan Jones | P79: Redesign | Q79: Redesign | R79: Not Started | S79: 46269 | V79: STRY0147198 | W79: 46276 | Z79: June 26 | AE79: Complete | AF79: 46234 | AG79: 46199 | AH79: 46199 | AI79: Not Started | AJ79: 46248 | AK79: 46248 | AM79: Not Started | AN79: 46254 | AO79: 46254 | AQ79: Not Started | AR79: 46295 | AS79: 46295 | AU79: N/a | AX79: Yes | BA79: Item | BB79: sites/ext-AonNFPIntegration/Lists/ITSM Integration InScope Inventory
A80: RM054 | B80: Catalog Item | C80: Request New Distribution List | D80: Olivia | E80: 2.2 | F80: 2.2 | N80: Create request for a new distribution list | O80: Donald Barksdale | P80: Adopt | Q80: Redesign | R80: On Hold | S80: 46258 | T80: Confirmation needed on future-state fulfillment path; Discussed with Donald, Eleanor, & Frank week of 7/13 & open email thread with IAM / Messaging team from 7/7, followed up on 7/17. | U80: Frank confirmed over email 7/15: This is something that can be handed to Accenture for fulfillment, we can move this to an automated process and retire these catalog items | W80: 46262 | X80: Create New Shared Mailbox | Y80: Soumendu Kumar Singh | Z80: July 7 | AB80: • Donald Barksdale • Nick Pilisko • Stephanie Lujan • Michael Kruger | AE80: In Progress | AF80: 46234 | AG80: 46241 | AI80: Not Started | AJ80: 46265 | AK80: 46265 | AM80: Not Started | AN80: 46268 | AO80: 46268 | AQ80: Not Started | AR80: 46295 | AS80: 46295 | AU80: N/a | AV80: =TRUE() -> TRUE | AX80: Yes | BA80: Item | BB80: sites/ext-AonNFPIntegration/Lists/ITSM Integration InScope Inventory
A81: RM055 | B81: Catalog Item | C81: Title/Manager Change | D81: Javier | E81: 1.2 | F81: 1.2 | N81: Technology Staff Change Request. | O81: Antowan Jones | P81: Redesign | Q81: Redesign | R81: Not Started | S81: 46269 | V81: STRY0147199 | W81: 46276 | Z81: June 26 | AE81: Complete | AF81: 46234 | AG81: 46199 | AH81: 46199 | AI81: Not Started | AJ81: 46248 | AK81: 46248 | AM81: Not Started | AN81: 46254 | AO81: 46254 | AQ81: Not Started | AR81: 46295 | AS81: 46295 | AU81: N/a | BA81: Item | BB81: sites/ext-AonNFPIntegration/Lists/ITSM Integration InScope Inventory
A82: RM056 | B82: Catalog Item | C82: Amex Purchase Card Application Form | D82: Tarun | E82: 1.2 | F82: 1.2 | G82: Complete | H82: On Hold | N82: Amex Purchase Card application form | O82: Kelly Cecchini | P82: Redesign | Q82: Redesign | R82: Ready for Testing | S82: 46248 | W82: 46254 | Z82: July 13 | AE82: Complete | AF82: 46234 | AG82: 46234 | AH82: 46234 | AI82: In Progress | AJ82: 46248 | AK82: 46266 | AL82: 46266 | AM82: Not Started | AN82: 46260 | AO82: 46269 | AQ82: Not Started | AR82: 46295 | AS82: 46295 | AU82: N/a | BA82: Item | BB82: sites/ext-AonNFPIntegration/Lists/ITSM Integration InScope Inventory
A83: RM057 | B83: Catalog Item | C83: Password Reset | D83: Javier | E83: 0 | F83: 0 | N83: Request a password to be reset for a service or an application. | O83: Donald Barksdale | P83: Adopt | Q83: Adopt | R83: Adopt - No Build Needed | X83: N/a - done outside of ServiceNow for future state | Y83: -- | Z83: July 7 | AB83: • Donald Barksdale • Nick Pilisko • Stephanie Lujan • Michael Kruger | AE83: Complete | AF83: 46234 | AG83: 46234 | AH83: 46234 | AI83: Complete | AJ83: 46234 | AK83: 46234 | AL83: 46234 | AM83: Not Started | AQ83: Not Started | AR83: 46295 | AS83: 46295 | AU83: N/a | BA83: Item | BB83: sites/ext-AonNFPIntegration/Lists/ITSM Integration InScope Inventory
A84: RM058 | B84: Catalog Item | C84: Zoom | D84: Tarun | E84: 2.1 | F84: 2.1 | N84: Request Zoom assistance (add/remove/support) | O84: Kim Ragland | P84: Adapt | Q84: Adapt | R84: Ready for Build | S84: 46251 | W84: 46258 | X84: Application Generic Service Request | Y84: John Edridge, Simon Sankey | Z84: Application Related | AF84: 46234 | AG84: 46234 | AI84: Not Started | AJ84: 46255 | AK84: 46255 | AM84: Not Started | AN84: 46261 | AO84: 46261 | AQ84: Not Started | AR84: 46295 | AS84: 46295 | AU84: N/a | AX84: Yes | BA84: Item | BB84: sites/ext-AonNFPIntegration/Lists/ITSM Integration InScope Inventory
A85: RM059 | B85: Catalog Item | C85: GitHub Copilot License Request | D85: Javier | E85: 1.2 | F85: 1.2 | G85: Complete | H85: In Progress | I85: Not Started | N85: Request GitHub Copilot license | O85: Frank Natividad | P85: Adopt | Q85: Redesign | R85: In Build Progress | S85: 46246 | T85: Custom Field Development Required; Waiting on Client's Input | V85: STRY0147050 | W85: 46253 | X85: Hardware, Systems & Application Access | Y85: Simon Sankey | Z85: July 10 | AA85: Confirmed | AB85: Frank N. | AF85: 46234 | AG85: 46234 | AH85: 46234 | AI85: In Progress | AJ85: 46248 | AK85: 46259 | AM85: Not Started | AN85: 46260 | AO85: 46262 | AQ85: Not Started | AR85: 46295 | AS85: 46295 | AU85: N/a | BA85: Item | BB85: sites/ext-AonNFPIntegration/Lists/ITSM Integration InScope Inventory
A86: RM060 | B86: Catalog Item | C86: Request ServiceNow Group Membership | D86: Olivia | E86: 0 | F86: 0 | N86: Use this catalog item to request that a user be added to a group in ServiceNow. | O86: Jerry Jenkins | P86: Adopt | Q86: Adopt | R86: Adopt - No Build Needed | X86: ServiceNow Group Administration | Y86: Hemkesh Singh | Z86: July 10 | AE86: Complete | AF86: 46234 | AG86: 46234 | AH86: 46234 | AI86: Complete | AJ86: 46234 | AK86: 46234 | AL86: 46234 | AM86: Not Started | AN86: 46241 | AO86: 46241 | AQ86: Not Started | AR86: 46295 | AS86: 46295 | AU86: N/a | BA86: Item | BB86: sites/ext-AonNFPIntegration/Lists/ITSM Integration InScope Inventory
A87: RM061 | B87: Catalog Item | C87: Decommission Site Code | D87: Javier | E87: 1.1 | F87: 1.1 | G87: Complete | H87: Complete | I87: Complete | J87: Done (08/31) | K87: Pending | L87: Pending Impln. | M87: Pending Impln. | N87: Close a site code (office). All equipment has been removed and retired | O87: Robert Spadaro | P87: Redesign | Q87: Redesign | R87: UAT In Progress | S87: 46241 | V87: STRY0146629 | W87: 46246 | Z87: June 25 | AE87: Complete | AF87: 46234 | AG87: 46220 | AH87: 46220 | AI87: Complete | AJ87: 46241 | AK87: 46220 | AL87: 46220 | AM87: In Progress | AN87: 46253 | AO87: 46255 | AP87: 46255 | AQ87: Not Started | AR87: 46295 | AS87: 46295 | AT87: 46295 | AU87: N/a | AX87: Yes | BA87: Item | BB87: sites/ext-AonNFPIntegration/Lists/ITSM Integration InScope Inventory
A88: RM062 | B88: Catalog Item | C88: Salesforce CRM P/AM Record Request | D88: Sowmya | E88: 2.1 | F88: 2.1 | G88: Complete | H88: Complete | I88: In Progress | J88: Requested | N88: This form is used to add or update Producer/Account Manager (P/AM) records in Salesforce CRM. | O88: Kris Lipetsky | P88: Redesign | Q88: Redesign | R88: UAT In Progress | S88: 46255 | T88: Awaiting design decisions from Kris L.; Action item on Kris to provide the information by 7/13, email reminder sent on 7/13 requesting the information | V88: STRY0147039 | W88: 46262 | Z88: July 6 | AE88: Complete | AF88: 46234 | AG88: 46234 | AH88: 46259 | AI88: Complete | AJ88: 46255 | AK88: 46260 | AL88: 46260 | AM88: In Progress | AN88: 46261 | AO88: 46261 | AP88: 46265 | AQ88: Not Started | AR88: 46295 | AS88: 46295 | AU88: N/a | AV88: =TRUE() -> TRUE | BA88: Item | BB88: sites/ext-AonNFPIntegration/Lists/ITSM Integration InScope Inventory
A89: RM063 | B89: Catalog Item | C89: SBO Request for Onboarding | D89: Sowmya | E89: 1.2 | F89: 1.2 | G89: Complete | H89: Complete | I89: Complete | J89: Done | K89: Done | L89: Not Started | M89: Not Started | N89: This form is used to set up a new employee or contractor in any NFP office. Instructions: Complete Section I AND EITHER Section II or Section III. | O89: Antowan Jones | P89: Redesign | Q89: Redesign | R89: Complete | S89: 46248 | W89: 46255 | Z89: June 26 | AB89: Kris Lipetzky, Antowan Jones, John Stratton | AE89: Complete | AF89: 46234 | AG89: 46199 | AH89: 46199 | AI89: Complete | AJ89: 46241 | AK89: 46241 | AL89: 46247 | AM89: Complete | AN89: 46247 | AO89: 46247 | AP89: 46262 | AQ89: Not Started | AR89: 46295 | AS89: 46295 | AT89: 46295 | AU89: Available alone and in O&T OG | AV89: =TRUE() -> TRUE | BA89: Item | BB89: sites/ext-AonNFPIntegration/Lists/ITSM Integration InScope Inventory
A90: RM064 | B90: Catalog Item | C90: Complete Site Code Integration | D90: Javier | E90: 1.1 | F90: 1.1 | G90: Complete | H90: Complete | I90: Complete | J90: Done (08/31) | K90: Pending | L90: Pending Impln. | M90: Pending Impln. | N90: Mark the site Active, In Production and ready for QA testing | O90: Robert Spadaro | P90: Redesign | Q90: Redesign | R90: UAT In Progress | S90: 46241 | V90: STRY0146629 | W90: 46246 | Z90: June 25 | AB90: Ethan Kats Robert Spadaro | AE90: Complete | AF90: 46234 | AG90: 46216 | AH90: 46216 | AI90: Complete | AJ90: 46241 | AK90: 46220 | AL90: 46220 | AM90: In Progress | AN90: 46253 | AO90: 46255 | AP90: 46255 | AQ90: Not Started | AR90: 46295 | AS90: 46295 | AT90: 46295 | AU90: N/a | BA90: Item | BB90: sites/ext-AonNFPIntegration/Lists/ITSM Integration InScope Inventory
A91: RM065 | B91: Catalog Item | C91: AI Request Form | D91: Olivia | E91: 1.1 | F91: 1.1 | G91: Complete | H91: Complete | I91: Complete | J91: Done (08/31) | K91: Pending | L91: Pending Impln. | M91: Pending Impln. | N91: Please use this form to notify the NFP AI Governance Team about starting a new project using AI with a third-party vendor, or current or in-progress projects/vendors using or planning to use AI. | O91: Sulyman Alani | P91: Adopt | Q91: Redesign | R91: UAT In Progress | S91: 46234 | V91: STRY0146963 | W91: 46241 | AA91: Confirmed | AE91: Complete | AF91: 46234 | AG91: 46234 | AH91: 46237 | AI91: Complete | AJ91: 46241 | AK91: 46241 | AL91: 46241 | AM91: In Progress | AN91: 46247 | AO91: 46247 | AQ91: Not Started | AU91: N/a | AW91: Placeholder approval group for testing. Need to confirm rejection logic during UAT. | BA91: Item | BB91: sites/ext-AonNFPIntegration/Lists/ITSM Integration InScope Inventory
A92: RM066 | B92: Catalog Item | C92: Visual Studio Request (consolidated to Github Copilot License) | D92: Javier | E92: 2.1 | F92: 2.1 | N92: Request Visual Studio access/license | O92: Frank Natividad | P92: Adapt | Q92: Redesign | R92: In Design | S92: 46255 | W92: 46262 | X92: Application Generic Service Request | Y92: John Edridge, Simon Sankey | Z92: July 10 | AF92: 46234 | AG92: 46234 | AI92: Not Started | AJ92: 46255 | AK92: 46255 | AM92: Not Started | AN92: 46261 | AO92: 46261 | AQ92: Not Started | AR92: 46295 | AS92: 46295 | AU92: Available alone and in O&T OG | AV92: =TRUE() -> TRUE | BA92: Item | BB92: sites/ext-AonNFPIntegration/Lists/ITSM Integration InScope Inventory
A93: RM067 | B93: Catalog Item | C93: Salesforce Reactivate User Request | D93: Sowmya | E93: 2.1 | F93: 2.1 | G93: Complete | H93: Complete | I93: In Progress | J93: Requested | N93: This form is used to reactivate user in Salesforce CRM platform and must be submitted/approved by the user's manager or Regional Salesforce Champion. | O93: Kris Lipetsky | P93: Redesign | Q93: Redesign | R93: UAT In Progress | S93: 46255 | T93: Awaiting design decisions from Kris L.; Action item on Kris to provide the information by 7/13, email reminder sent on 7/13 requesting the information | V93: STRY0147039 | W93: 46262 | Z93: July 6 | AE93: Complete | AF93: 46234 | AG93: 46234 | AH93: 46259 | AI93: Complete | AJ93: 46255 | AK93: 46260 | AL93: 46260 | AM93: In Progress | AN93: 46261 | AO93: 46265 | AP93: 46265 | AQ93: Not Started | AR93: 46295 | AS93: 46295 | AT93: 46295 | AU93: N/a | BA93: Item | BB93: sites/ext-AonNFPIntegration/Lists/ITSM Integration InScope Inventory
A94: RM068 | B94: Catalog Item | C94: Azure Application SSO Configuration | D94: Sowmya | E94: 2.2 | F94: 2.2 | G94: Complete | H94: Complete | I94: In Progress | N94: Open a request for new Azure application configuration | O94: Andy Goss | P94: Redesign | Q94: Redesign | R94: Ready for Testing | S94: 46262 | U94: Will be built in Aon as a one-for-one re-creation of what is in NFP (aside from conforming to Aon standards) | V94: STRY0147127 | W94: 46269 | AE94: Complete | AF94: 46234 | AG94: 46234 | AH94: 46262 | AI94: Not Started | AJ94: 46265 | AK94: 46265 | AL94: 46266 | AM94: In Progress | AN94: 46268 | AO94: 46268 | AQ94: Not Started | AR94: 46295 | AS94: 46295 | AU94: N/a | BA94: Item | BB94: sites/ext-AonNFPIntegration/Lists/ITSM Integration InScope Inventory
A95: RM069 | B95: Catalog Item | C95: Browser Extension Request Form | D95: Javier | E95: 1.1 | F95: 1.1 | G95: N/A | H95: N/A | I95: N/A | J95: N/A | K95: N/A | N95: Submit this form to request a browser extension. | O95: John Stratton | P95: Adopt | Q95: Adopt | R95: UAT In Progress | S95: 46241 | T95: Awaiting confirmation on path forward from John S.; Email thread followed up on 7/14. | U95: Follow up session needed with John and Gary, this is owned by M365 on aon not security | W95: 46246 | X95: Web Browser - Request an Extension | Y95: Gary Mcnair | Z95: Awaiting Disposition Confirmation | AE95: Complete | AF95: 46234 | AG95: 46227 | AH95: 46227 | AI95: Complete | AJ95: 46241 | AK95: 46244 | AL95: 46244 | AM95: In Progress | AN95: 46253 | AO95: 46255 | AP95: 46255 | AQ95: Not Started | AR95: 46295 | AS95: 46295 | AU95: N/a | BA95: Item | BB95: sites/ext-AonNFPIntegration/Lists/ITSM Integration InScope Inventory
A96: RM070 | B96: Catalog Item | C96: ARS (Applied Rating Services) | D96: N/a - Descoped | E96: N/a - Descoped | F96: N/a - Descoped | N96: Create Request for ARS (Applied Rating Services) Assistance | O96: Teri Cote | P96: Redesign | Q96: Retire / Descoped | R96: Descoped | U96: Confirmed not needed by Teri via questionnaire email response on 25-Jun. Confirmed by Frank 7/13. | Z96: July 15 | AA96: Confirmed | AF96: 46234 | AJ96: 46248 | AK96: 46248 | AM96: Not Started | AN96: 46254 | AO96: 46254 | AQ96: Not Started | AR96: 46295 | AS96: 46295 | AU96: N/a | BA96: Item | BB96: sites/ext-AonNFPIntegration/Lists/ITSM Integration InScope Inventory
A97: RM071 | B97: Catalog Item | C97: Pathway | D97: N/a - Descoped | E97: N/a - Descoped | F97: N/a - Descoped | N97: Create Request for Pathway Assistance | O97: Chantale Roy | P97: Redesign | Q97: Retire / Descoped | R97: Descoped | S97: 46239 | T97: There was a request to deactivate this catalog item in NFP's ServiceNow instance (approved by the service owner) and it is currently not in use. Awaiting confirmation from Chantale R. on whether this catalog item should be retired / descoped or if build should commence. | U97: Design confirmed to be as-is via email. | W97: 46246 | AB97: Chantale Roy, Bonnie Jones | AE97: In Progress | AF97: 46234 | AG97: 46234 | AI97: Not Started | AJ97: 46241 | AK97: 46241 | AM97: Not Started | AN97: 46247 | AO97: 46247 | AQ97: Not Started | AU97: N/a | BA97: Item | BB97: sites/ext-AonNFPIntegration/Lists/ITSM Integration InScope Inventory
A98: RM072 | B98: Catalog Item | C98: New ServiceNow Group Request | D98: Olivia | E98: 0 | F98: 0 | N98: In ServiceNow, a Group is a collection of users with a shared role or purpose, used to streamline task assignments, approvals, notifications, and access control. | O98: Jerry Jenkins | P98: Adopt | Q98: Adopt | R98: Adopt - No Build Needed | X98: ServiceNow Group Administration | Y98: Hemkesh Singh | Z98: July 10 | AE98: Complete | AF98: 46234 | AG98: 46234 | AH98: 46234 | AI98: Complete | AJ98: 46234 | AK98: 46234 | AL98: 46234 | AM98: Not Started | AN98: 46241 | AO98: 46241 | AQ98: Not Started | AR98: 46295 | AS98: 46295 | AU98: N/a | BA98: Item | BB98: sites/ext-AonNFPIntegration/Lists/ITSM Integration InScope Inventory
A99: RM073 | B99: Catalog Item | C99: Technology Third Party Users Access | D99: Javier | E99: 1.1 | F99: 1.2 | N99: Used to onboarding Third-party Users for Technology (Vendors) | O99: Antowan Jones | P99: Redesign | Q99: Redesign | R99: Not Started | S99: 46269 | W99: 46276 | Z99: June 26 | AE99: Complete | AF99: 46234 | AG99: 46199 | AH99: 46199 | AI99: Not Started | AJ99: 46241 | AK99: 46241 | AM99: Not Started | AN99: 46247 | AO99: 46247 | AQ99: Not Started | AR99: 46295 | AS99: 46295 | AU99: N/a | BA99: Item | BB99: sites/ext-AonNFPIntegration/Lists/ITSM Integration InScope Inventory
A100: RM074 | B100: Catalog Item | C100: TM1 | D100: N/a - Descoped | E100: N/a - Descoped | F100: N/a - Descoped | N100: Create a request for TM1 assistance. | O100: Bobbie Johnson | P100: Adopt | Q100: Retire / Descoped | R100: Descoped | X100: Application Generic Service Request | Y100: John Edridge, Simon Sankey | Z100: N/a - Descoped | AA100: Confirmed | AF100: 46234 | AJ100: 46255 | AK100: 46255 | AM100: Not Started | AN100: 46261 | AO100: 46261 | AQ100: Not Started | AR100: 46295 | AS100: 46295 | AU100: N/a | BA100: Item | BB100: sites/ext-AonNFPIntegration/Lists/ITSM Integration InScope Inventory
A101: RM075 | B101: Catalog Item | C101: ServiceNow Non-Production Access Request | D101: Olivia | E101: 0 | F101: 0 | N101: Request Non-Production ServiceNow Access | O101: Jerry Jenkins | P101: Adopt | Q101: Adopt | R101: Adopt - No Build Needed | X101: Hardware, Systems & Application Access | Y101: Simon Sankey | Z101: July 10 | AE101: Complete | AF101: 46234 | AG101: 46234 | AH101: 46234 | AI101: Complete | AJ101: 46234 | AK101: 46234 | AL101: 46234 | AM101: Not Started | AN101: 46241 | AO101: 46241 | AQ101: Not Started | AR101: 46295 | AS101: 46295 | AU101: N/a | BA101: Item | BB101: sites/ext-AonNFPIntegration/Lists/ITSM Integration InScope Inventory
A102: RM076 | B102: Catalog Item | C102: Email Rebrand Application List | D102: Olivia | E102: 1.1 | F102: 1.1 | G102: Complete | H102: Complete | I102: Complete | J102: Done (08/31) | K102: Done (08/31) | L102: Pending Impln. | M102: Pending Impln. | N102: Create a request to generate the application list for users included in an email rebrand | O102: Jerry Jenkins, Sherrie Wooten | P102: Redesign | Q102: Redesign | R102: UAT In Progress | S102: 46241 | U102: Awaiting design confirmation via email | V102: STRY0146966 | W102: 46248 | Z102: July 10 | AB102: Jerry Jenkins, Sherrie Wooten, Bob Johnston | AE102: Complete | AF102: 46234 | AG102: 46234 | AH102: 46234 | AI102: Complete | AJ102: 46241 | AK102: 46241 | AL102: 46241 | AM102: In Progress | AN102: 46247 | AO102: 46247 | AQ102: Not Started | AU102: N/a | BA102: Item | BB102: sites/ext-AonNFPIntegration/Lists/ITSM Integration InScope Inventory
...

Sheet Instructions
A1: Nitin Shetty (US) Sowmya M R (US) I created a separate tab for AG Mapping, AG Inventory, and Group Membership. Instruction on how to populate: Confirm the group names and group manager + members with the NFP Owner Go into the tracker and navigate to "Assignment Group Inventory" tab Check if the group you want to add already created If not created, add the Assignment Group Name to the next free AG ID, and populate Manager's name; Ensure adherence to the Aon naming standard; pay attention to Approval and Support groups, and name your groups according to the use case If created, grab the AG ID Navigate to the AG Mapping to Items tab: Find the Target Aon Catalog Item in column C that your group needs to be used for Populate the grabbed AG ID into the AG ID column If multiple groups are in the workflow, add new line item on the tab, and populate the AON ID in the newly created line item, it will pull the Target Aon Catalog Item name, and then populate the next AG ID in that line, populate manager Navigate to Group Membership tab Populate the grabbed AG ID into the new line item Each line item = one group member Populate group members

Sheet AGs to Create in PROD+TEST+DEV
A1: AG ID | B1: Assignment Group Name | C1: Group Manager | D1: Manager's Email | E1: Short Description | F1: Service | G1: Prod | H1: Test | I1: Dev
A2: AG001 | B2: Global-NFP AI Working Group-Approval | C2: Sulyman Al-Ani | D2: sulyman.alani@nfp.co.uk | E2: Approval group for the following catalog item deployed as part of NFP integration: NFP - AI Governance Review | F2: NFP
A3: AG002 | B3: Global-NFP Amex Card Management-Support | C3: Kelly Cecchini | D3: kelly.cecchini@nfp.com | E3: Support group for the following catalog item deployed as part of NFP integration: NFP - Amex Purchase Card Application Form | F3: NFP
A4: AG003 | B4: Global-NFP Application Engineering-Support | C4: Shashank Karanje | D4: shashank.karanje@nfp.com | E4: Support group to be deployed as part of NFP integration. Support group to receive incident tickets as part of NFP Blueprint and NFP Connect Integrations | F4: NFP
A5: AG004 | B5: Global-NFP Azure DevOps Engineering-Support | C5: Frank Natividad | D5: frank.natividad@nfp.com | E5: Support group for the following catalog item deployed as part of NFP integration: NFP - DevOps Support | F5: NFP
A6: AG005 | B6: Global-NFP Benefits Commission Processing-Support | C6: Kris Lipetzky | D6: klipetzky@nfp.com | E6: Support group for the following catalog item deployed as part of NFP integration: NFP - Carrier Statement Mass Delete Request, NFP - Producer Additions & Terminations, NFP - Salesforce Policy Update | F6: NFP
A7: AG007 | B7: Global-NFP CRM Services-Support | C7: Kris Lipetzky | D7: klipetzky@nfp.com | E7: Support group for the following catalog item deployed as part of NFP integration: NFP - Application Users List Generation for Email Rebrand, NFP - Producer Additions & Terminations, NFP - Return from LOA, NFP - Salesforce Access Request, NFP - SBO Request for Onboarding | F7: NFP
A8: AG009 | B8: Global-NFP CyberSecurity-Support | C8: John Stratton | D8: john.stratton@nfp.com | E8: Support group for the following catalog item deployed as part of NFP integration: NFP - Remote Work Request | F8: NFP
A9: AG012 | B9: Global-NFP Go Anywhere SFTP-Support | C9: Enoch Tong | D9: etong@nfp.com | E9: Support group for the following catalog item deployed as part of NFP integration: NFP - Go Anywhere Request | F9: NFP
A10: AG013 | B10: Global-NFP Time Tracker-Support | C10: Kirk Oswalt | D10: kirk.oswalt@nfp.com | E10: Support group for the following catalog item deployed as part of NFP integration: NFP - Time Tracker | F10: NFP
A11: AG015 | B11: Global-NFP P&C-App-Support | C11: Teri Cote | D11: teri.cote@nfp.com | E11: Support group for the following catalog item deployed as part of NFP integration: NFP - Name / Email Change Request, NFP - Return from LOA | F11: NFP
A12: AG016 | B12: Global-NFP Plan Document-Support | C12: Chase Cannon | D12: ccannon@nfp.com | E12: Support group for the following catalog item deployed as part of NFP integration: NFP - Plan Document Request | F12: NFP
A13: AG023 | B13: Global-NFP Technology Logistics-Support | C13: Kimberley Ragland | D13: kragland@nfp.com | E13: Support group for the following catalog item deployed as part of NFP integration: NFP - Hardware Return, NFP - Onboarding Hardware Request | F13: NFP
... A40: AG058 | B40: Global-NFP Third Party Access-Approval | C40: Steve Chapman | D40: schapman@nfp.com | E40: Approval group for the following catalog item deployed as part of NFP integration: NFP - Technology Third Party Users Access | F40: NFP

Sheet AGs to Create in TEST+DEV
A1: AG ID | B1: Assignment Group Name | C1: Group Manager | D1: Prod | E1: Test | F1: Dev
A2: AG011 | B2: Global-NFP Financial Systems-Support | C2: Bobbie Johnson | D2: Created | E2: Not Created | F2: Not Created
A3: AG014 | B3: Global-NFP Networks-Support | C3: Robert Spadaro | D3: Created | E3: Not Created | F3: Not Created
A4: AG019 | B4: Global-NFP Service Desk Tier 1-Support | C4: Nick Pilisko | D4: Created | E4: Not Created | F4: Not Created
A5: AG021 | B5: Global-NFP Service Desk Tier 3 Core Services-Support | C5: Steve Chapman | D5: Created | E5: Not Created | F5: Not Created
A6: AG022 | B6: Global-NFP ServiceNow-Support | C6: Antowan Jones | D6: Created | E6: Not Created | F6: Not Created
A7: AG032 | B7: Global-NFP Data Management-Support | C7: Antowan Jones | D7: Created | E7: Not Created | F7: Not Created
A8: AG037 | B8: Global-NFP MGA-Support | C8: Regina Riedel | D8: Created | E8: Not Created | F8: Not Created

Sheet Group Membership
A1: AG ID | B1: Assignment Group Name | C1: First Name | D1: Last Name | E1: Email
A2: AG001 | B2: Global-NFP AI Working Group-Approval | C2: Sulyman | D2: Al-Ani | E2: sulyman.alani@nfp.co.uk
A3: AG001 | B3: Global-NFP AI Working Group-Approval | C3: Mark | D3: Grosvenor | E3: mark.grosvenor@nfp.com
A4: AG001 | B4: Global-NFP AI Working Group-Approval | C4: Tom | D4: Claridge | E4: tom.claridge@nfp.co.uk
A5: AG001 | B5: Global-NFP AI Working Group-Approval | C5: David | D5: Horn | E5: dhorn@nfp.com
A6: AG001 | B6: Global-NFP AI Working Group-Approval | C6: James | D6: Fritz | E6: james.fritz@nfp.com
A7: AG001 | B7: Global-NFP AI Working Group-Approval | C7: Jayaprakash | D7: Subramaniam | E7: jsubramaniam@nfp.com
A8: AG002 | B8: Global-NFP Amex Card Management-Support | C8: Eugene | D8: Melino | E8: emelino@nfp.com
A9: AG002 | B9: Global-NFP Amex Card Management-Support | C9: Kelly | D9: Cecchini | E9: kelly.cecchini@nfp.com
A10: AG002 | B10: Global-NFP Amex Card Management-Support | C10: Nancy | D10: Govea | E10: nancy.govea@nfp.com
A11: AG002 | B11: Global-NFP Amex Card Management-Support | C11: Megan | D11: Goad | E11: megan.goad@nfp.com
A12: AG003 | B12: Global-NFP Application Engineering-Support | C12: Balajiprasad | D12: Ramesh | E12: bramesh@nfp.com
... A499: AG058 | B499: Global-NFP Third Party Access-Approval | C499: Tomson | D499: John | E499: tomson.john@nfp.com
B501: =IF($A501="","",IFERROR(IF(INDEX('AGs to Create in TEST+DEV'!$B$2:$B$220,MATCH($A501,'AGs to Create in TEST+DEV'!$A$2:$A$220,0))="","",INDEX('AGs to Create in TEST+DEV'!$B$2:$B$220,MATCH($A501,'AGs to Create in TEST+DEV'!$A$2:$A$220,0))),"Not in inventory"))
B502: =IF($A502="","",IFERROR(IF(INDEX('AGs to Create in TEST+DEV'!$B$2:$B$220,MATCH($A502,'AGs to Create in TEST+DEV'!$A$2:$A$220,0))="","",INDEX('AGs to Create in TEST+DEV'!$B$2:$B$220,MATCH($A502,'AGs to Create in TEST+DEV'!$A$2:$A$220,0))),"Not in inventory"))
B503: =IF($A503="","",IFERROR(IF(INDEX('AGs to Create in TEST+DEV'!$B$2:$B$220,MATCH($A503,'AGs to Create in TEST+DEV'!$A$2:$A$220,0))="","",INDEX('AGs to Create in TEST+DEV'!$B$2:$B$220,MATCH($A503,'AGs to Create in TEST+DEV'!$A$2:$A$220,0))),"Not in inventory"))
B504: =IF($A504="","",IFERROR(IF(INDEX('AGs to Create in TEST+DEV'!$B$2:$B$220,MATCH($A504,'AGs to Create in TEST+DEV'!$A$2:$A$220,0))="","",INDEX('AGs to Create in TEST+DEV'!$B$2:$B$220,MATCH($A504,'AGs to Create in TEST+DEV'!$A$2:$A$220,0))),"Not in inventory"))
B505: =IF($A505="","",IFERROR(IF(INDEX('AGs to Create in TEST+DEV'!$B$2:$B$220,MATCH($A505,'AGs to Create in TEST+DEV'!$A$2:$A$220,0))="","",INDEX('AGs to Create in TEST+DEV'!$B$2:$B$220,MATCH($A505,'AGs to Create in TEST+DEV'!$A$2:$A$220,0))),"Not in inventory"))
B506: =IF($A506="","",IFERROR(IF(INDEX('AGs to Create in TEST+DEV'!$B$2:$B$220,MATCH($A506,'AGs to Create in TEST+DEV'!$A$2:$A$220,0))="","",INDEX('AGs to Create in TEST+DEV'!$B$2:$B$220,MATCH($A506,'AGs to Create in TEST+DEV'!$A$2:$A$220,0))),"Not in inventory"))
B507: =IF($A507="","",IFERROR(IF(INDEX('AGs to Create in TEST+DEV'!$B$2:$B$220,MATCH($A507,'AGs to Create in TEST+DEV'!$A$2:$A$220,0))="","",INDEX('AGs to Create in TEST+DEV'!$B$2:$B$220,MATCH($A507,'AGs to Create in TEST+DEV'!$A$2:$A$220,0))),"Not in inventory"))
B508: =IF($A508="","",IFERROR(IF(INDEX('AGs to Create in TEST+DEV'!$B$2:$B$220,MATCH($A508,'AGs to Create in TEST+DEV'!$A$2:$A$220,0))="","",INDEX('AGs to Create in TEST+DEV'!$B$2:$B$220,MATCH($A508,'AGs to Create in TEST+DEV'!$A$2:$A$220,0))),"Not in inventory"))
B509: =IF($A509="","",IFERROR(IF(INDEX('AGs to Create in TEST+DEV'!$B$2:$B$220,MATCH($A509,'AGs to Create in TEST+DEV'!$A$2:$A$220,0))="","",INDEX('AGs to Create in TEST+DEV'!$B$2:$B$220,MATCH($A509,'AGs to Create in TEST+DEV'!$A$2:$A$220,0))),"Not in inventory"))
B510: =IF($A510="","",IFERROR(IF(INDEX('AGs to Create in TEST+DEV'!$B$2:$B$220,MATCH($A510,'AGs to Create in TEST+DEV'!$A$2:$A$220,0))="","",INDEX('AGs to Create in TEST+DEV'!$B$2:$B$220,MATCH($A510,'AGs to Create in TEST+DEV'!$A$2:$A$220,0))),"Not in inventory"))
B511: =IF($A511="","",IFERROR(IF(INDEX('AGs to Create in TEST+DEV'!$B$2:$B$220,MATCH($A511,'AGs to Create in TEST+DEV'!$A$2:$A$220,0))="","",INDEX('AGs to Create in TEST+DEV'!$B$2:$B$220,MATCH($A511,'AGs to Create in TEST+DEV'!$A$2:$A$220,0))),"Not in inventory"))
B512: =IF($A512="","",IFERROR(IF(INDEX('AGs to Create in TEST+DEV'!$B$2:$B$220,MATCH($A512,'AGs to Create in TEST+DEV'!$A$2:$A$220,0))="","",INDEX('AGs to Create in TEST+DEV'!$B$2:$B$220,MATCH($A512,'AGs to Create in TEST+DEV'!$A$2:$A$220,0))),"Not in inventory"))
... B526: =IF($A526="","",IFERROR(IF(INDEX('AGs to Create in TEST+DEV'!$B$2:$B$220,MATCH($A526,'AGs to Create in TEST+DEV'!$A$2:$A$220,0))="","",INDEX('AGs to Create in TEST+DEV'!$B$2:$B$220,MATCH($A526,'AGs to Create in TEST+DEV'!$A$2:$A$220,0))),"Not in inventory"))

Sheet ASSIGNMENT GROUPS
C3: Number | D3: Item Name | E3: RITM Number | F3: ASSIGNMENT GROUP NAME | G3: Status | H3: PwC Owner | I3: Cloned Down | J3: ITIL Assigned
F4: RITM5301885: Global-Financial Systems-Support
F6: RITM5302297: Global-Amex Card Management-Support
F8: RITM5299949: Global-CRM Services-Support
F10: RITM5299934: Global-Plan Doc-Support
F12: RITM5307167: Global-Azure DevOps Engineering-Support
F14: RITM5307160 : Global-Quality Assurance Infrastructure-Support
F16: RITM5294435: Global-Service Desk Tier 3 Core Services-Support
F18: RITM5294404: Global-NFP Networks-Support
F20: RITM5294415: Global-NFP Data Management-Support
